{"VariableList":{"ErrorMsg":"success","ErrorCode":"0"},"DatasetList":{"DS_COUR030":[{"submattFg":"U0209003","stgNeceGrpNm":"","sideTotalPnt":2.0,"sbjtChgFg":"","subDgnTotalPnt":null,"sy62shtmRcomYn":"","abeekSubmattFgNm":"","sustLsnFgNm":"교필","sy12shtmRcomYn":"","sy42shtmRcomYn":"","abeekInspPracPntCnt":null,"genrl1stgNeceSbjtCnt":null,"abeekSustLsnFg":"","abeekDetaSubmattFg":"","sy51shtmRcomYn":"","abeekSustLsnFgNm":"","sy11shtmRcomYn":"","abeekTheoPntCnt":null,"sy31shtmRcomYn":"","submattFgNm":"기초과목","sbjtCd":"1042","subTheoTotalPnt":null,"mjCd":"DS03008002001","sy61shtmRcomYn":"","sy22shtmRcomYn":"○","mjCdNm":"의학전공(과)","sustLsnFg":"U0208002","sy52shtmRcomYn":"","sy21shtmRcomYn":"","sbjtChgFgNm":"","abeekDgnPntCnt":null,"sbjtKorNm":"현대심리학","sy41shtmRcomYn":"","genrl1stgNeceGrp":"","abeekGrpChoice":"","abeekSubmattFg":"","theoFgNm":"이론","abeekDetaSubmattFgNm":"","sy32shtmRcomYn":"","openTm":2.0,"pnt":2.0,"sbjtId":"1042","abeekChoiceSbjtCnt":null,"corsYy":"2019","subInspTotalPnt":null,"abeekGrpNm":"","rowStatus":1,"theoFg":"U0210001","curiNo":"2019106227"},{"submattFg":"U0209003","stgNeceGrpNm":"","sideTotalPnt":2.0,"sbjtChgFg":"","subDgnTotalPnt":null,"sy62shtmRcomYn":"","abeekSubmattFgNm":"","sustLsnFgNm":"교필","sy12shtmRcomYn":"","sy42shtmRcomYn":"","abeekInspPracPntCnt":null,"genrl1stgNeceSbjtCnt":null,"abeekSustLsnFg":"","abeekDetaSubmattFg":"","sy51shtmRcomYn":"","abeekSustLsnFgNm":"","sy11shtmRcomYn":"","abeekTheoPntCnt":null,"sy31shtmRcomYn":"","submattFgNm":"기초과목","sbjtCd":"1042","subTheoTotalPnt":null,"mjCd":"DS03008002001","sy61shtmRcomYn":"","sy22shtmRcomYn":"○","mjCdNm":"의학전공(과)","sustLsnFg":"U0208002","sy52shtmRcomYn":"","sy21shtmRcomYn":"","sbjtChgFgNm":"","abeekDgnPntCnt":null,"sbjtKorNm":"현대심리학","sy41shtmRcomYn":"","genrl1stgNeceGrp":"","abeekGrpChoice":"","abeekSubmattFg":"","theoFgNm":"이론","abeekDetaSubmattFgNm":"","sy32shtmRcomYn":"","openTm":2.0,"pnt":2.0,"sbjtId":"1042","abeekChoiceSbjtCnt":null,"corsYy":"2019","subInspTotalPnt":null,"abeekGrpNm":"","rowStatus":1,"theoFg":"U0210001","curiNo":"2019106243"},{"submattFg":"U0209003","stgNeceGrpNm":"택C2","sideTotalPnt":3.0,"sbjtChgFg":"","subDgnTotalPnt":null,"sy62shtmRcomYn":"","abeekSubmattFgNm":"","sustLsnFgNm":"교필","sy12shtmRcomYn":"","sy42shtmRcomYn":"","abeekInspPracPntCnt":null,"genrl1stgNeceSbjtCnt":2.0,"abeekSustLsnFg":"","abeekDetaSubmattFg":"","sy51shtmRcomYn":"","abeekSustLsnFgNm":"","sy11shtmRcomYn":"","abeekTheoPntCnt":null,"sy31shtmRcomYn":"","submattFgNm":"기초과목","sbjtCd":"BIO102","subTheoTotalPnt":null,"mjCd":"DS03008002001","sy61shtmRcomYn":"","sy22shtmRcomYn":"○","mjCdNm":"의학전공(과)","sustLsnFg":"U0208002","sy52shtmRcomYn":"","sy21shtmRcomYn":"","sbjtChgFgNm":"","abeekDgnPntCnt":null,"sbjtKorNm":"생물학2","sy41shtmRcomYn":"","genrl1stgNeceGrp":"C","abeekGrpChoice":"","abeekSubmattFg":"","theoFgNm":"이론","abeekDetaSubmattFgNm":"","sy32shtmRcomYn":"","openTm":3.0,"pnt":3.0,"sbjtId":"450","abeekChoiceSbjtCnt":null,"corsYy":"2019","subInspTotalPnt":null,"abeekGrpNm":"","rowStatus":1,"theoFg":"U0210001","curiNo":"2019106228"},{"submattFg":"U0209003","stgNeceGrpNm":"택C2","sideTotalPnt":1.0,"sbjtChgFg":"","subDgnTotalPnt":null,"sy62shtmRcomYn":"","abeekSubmattFgNm":"","sustLsnFgNm":"교필","sy12shtmRcomYn":"","sy42shtmRcomYn":"","abeekInspPracPntCnt":null,"genrl1stgNeceSbjtCnt":2.0,"abeekSustLsnFg":"","abeekDetaSubmattFg":"","sy51shtmRcomYn":"","abeekSustLsnFgNm":"","sy11shtmRcomYn":"","abeekTheoPntCnt":null,"sy31shtmRcomYn":"","submattFgNm":"기초과목","sbjtCd":"BIO103","subTheoTotalPnt":null,"mjCd":"DS03008002001","sy61shtmRcomYn":"","sy22shtmRcomYn":"○","mjCdNm":"의학전공(과)","sustLsnFg":"U0208002","sy52shtmRcomYn":"","sy21shtmRcomYn":"","sbjtChgFgNm":"","abeekDgnPntCnt":null,"sbjtKorNm":"생물학실험2","sy41shtmRcomYn":"","genrl1stgNeceGrp":"C","abeekGrpChoice":"","abeekSubmattFg":"","theoFgNm":"실습","abeekDetaSubmattFgNm":"","sy32shtmRcomYn":"","openTm":2.0,"pnt":1.0,"sbjtId":"452","abeekChoiceSbjtCnt":null,"corsYy":"2019","subInspTotalPnt":null,"abeekGrpNm":"","rowStatus":1,"theoFg":"U0210002","curiNo":"2019106229"},{"submattFg":"U0209003","stgNeceGrpNm":"택B2","sideTotalPnt":3.0,"sbjtChgFg":"","subDgnTotalPnt":null,"sy62shtmRcomYn":"","abeekSubmattFgNm":"","sustLsnFgNm":"교필","sy12shtmRcomYn":"","sy42shtmRcomYn":"","abeekInspPracPntCnt":null,"genrl1stgNeceSbjtCnt":2.0,"abeekSustLsnFg":"","abeekDetaSubmattFg":"","sy51shtmRcomYn":"","abeekSustLsnFgNm":"","sy11shtmRcomYn":"○","abeekTheoPntCnt":null,"sy31shtmRcomYn":"","submattFgNm":"기초과목","sbjtCd":"BIO112","subTheoTotalPnt":null,"mjCd":"DS03008002001","sy61shtmRcomYn":"","sy22shtmRcomYn":"","mjCdNm":"의학전공(과)","sustLsnFg":"U0208002","sy52shtmRcomYn":"","sy21shtmRcomYn":"","sbjtChgFgNm":"","abeekDgnPntCnt":null,"sbjtKorNm":"생물학1","sy41shtmRcomYn":"","genrl1stgNeceGrp":"B","abeekGrpChoice":"","abeekSubmattFg":"","theoFgNm":"이론","abeekDetaSubmattFgNm":"","sy32shtmRcomYn":"","openTm":3.0,"pnt":3.0,"sbjtId":"449","abeekChoiceSbjtCnt":null,"corsYy":"2019","subInspTotalPnt":null,"abeekGrpNm":"","rowStatus":1,"theoFg":"U0210001","curiNo":"2019106230"},{"submattFg":"U0209003","stgNeceGrpNm":"택B2","sideTotalPnt":1.0,"sbjtChgFg":"","subDgnTotalPnt":null,"sy62shtmRcomYn":"","abeekSubmattFgNm":"","sustLsnFgNm":"교필","sy12shtmRcomYn":"","sy42shtmRcomYn":"","abeekInspPracPntCnt":null,"genrl1stgNeceSbjtCnt":2.0,"abeekSustLsnFg":"","abeekDetaSubmattFg":"","sy51shtmRcomYn":"","abeekSustLsnFgNm":"","sy11shtmRcomYn":"○","abeekTheoPntCnt":null,"sy31shtmRcomYn":"","submattFgNm":"기초과목","sbjtCd":"BIO113","subTheoTotalPnt":null,"mjCd":"DS03008002001","sy61shtmRcomYn":"","sy22shtmRcomYn":"","mjCdNm":"의학전공(과)","sustLsnFg":"U0208002","sy52shtmRcomYn":"","sy21shtmRcomYn":"","sbjtChgFgNm":"","abeekDgnPntCnt":null,"sbjtKorNm":"생물학실험1","sy41shtmRcomYn":"","genrl1stgNeceGrp":"B","abeekGrpChoice":"","abeekSubmattFg":"","theoFgNm":"실습","abeekDetaSubmattFgNm":"","sy32shtmRcomYn":"","openTm":2.0,"pnt":1.0,"sbjtId":"451","abeekChoiceSbjtCnt":null,"corsYy":"2019","subInspTotalPnt":null,"abeekGrpNm":"","rowStatus":1,"theoFg":"U0210002","curiNo":"2019106231"},{"submattFg":"U0209003","stgNeceGrpNm":"","sideTotalPnt":3.0,"sbjtChgFg":"","subDgnTotalPnt":null,"sy62shtmRcomYn":"","abeekSubmattFgNm":"","sustLsnFgNm":"교필","sy12shtmRcomYn":"○","sy42shtmRcomYn":"","abeekInspPracPntCnt":null,"genrl1stgNeceSbjtCnt":null,"abeekSustLsnFg":"","abeekDetaSubmattFg":"","sy51shtmRcomYn":"","abeekSustLsnFgNm":"","sy11shtmRcomYn":"","abeekTheoPntCnt":null,"sy31shtmRcomYn":"","submattFgNm":"기초과목","sbjtCd":"CCMP105","subTheoTotalPnt":null,"mjCd":"DS03008002001","sy61shtmRcomYn":"","sy22shtmRcomYn":"","mjCdNm":"의학전공(과)","sustLsnFg":"U0208002","sy52shtmRcomYn":"","sy21shtmRcomYn":"","sbjtChgFgNm":"","abeekDgnPntCnt":null,"sbjtKorNm":"데이터분석기초","sy41shtmRcomYn":"","genrl1stgNeceGrp":"","abeekGrpChoice":"","abeekSubmattFg":"","theoFgNm":"이론","abeekDetaSubmattFgNm":"","sy32shtmRcomYn":"","openTm":3.0,"pnt":3.0,"sbjtId":"20150688","abeekChoiceSbjtCnt":null,"corsYy":"2019","subInspTotalPnt":null,"abeekGrpNm":"","rowStatus":1,"theoFg":"U0210001","curiNo":"2019106232"},{"submattFg":"U0209003","stgNeceGrpNm":"택B2","sideTotalPnt":3.0,"sbjtChgFg":"","subDgnTotalPnt":null,"sy62shtmRcomYn":"","abeekSubmattFgNm":"","sustLsnFgNm":"교필","sy12shtmRcomYn":"","sy42shtmRcomYn":"","abeekInspPracPntCnt":null,"genrl1stgNeceSbjtCnt":2.0,"abeekSustLsnFg":"","abeekDetaSubmattFg":"","sy51shtmRcomYn":"","abeekSustLsnFgNm":"","sy11shtmRcomYn":"○","abeekTheoPntCnt":null,"sy31shtmRcomYn":"","submattFgNm":"기초과목","sbjtCd":"CHEM112","subTheoTotalPnt":null,"mjCd":"DS03008002001","sy61shtmRcomYn":"","sy22shtmRcomYn":"","mjCdNm":"의학전공(과)","sustLsnFg":"U0208002","sy52shtmRcomYn":"","sy21shtmRcomYn":"","sbjtChgFgNm":"","abeekDgnPntCnt":null,"sbjtKorNm":"화학1","sy41shtmRcomYn":"","genrl1stgNeceGrp":"B","abeekGrpChoice":"","abeekSubmattFg":"","theoFgNm":"이론","abeekDetaSubmattFgNm":"","sy32shtmRcomYn":"","openTm":3.0,"pnt":3.0,"sbjtId":"991","abeekChoiceSbjtCnt":null,"corsYy":"2019","subInspTotalPnt":null,"abeekGrpNm":"","rowStatus":1,"theoFg":"U0210001","curiNo":"2019106233"},{"submattFg":"U0209003","stgNeceGrpNm":"택C2","sideTotalPnt":3.0,"sbjtChgFg":"","subDgnTotalPnt":null,"sy62shtmRcomYn":"","abeekSubmattFgNm":"","sustLsnFgNm":"교필","sy12shtmRcomYn":"○","sy42shtmRcomYn":"","abeekInspPracPntCnt":null,"genrl1stgNeceSbjtCnt":2.0,"abeekSustLsnFg":"","abeekDetaSubmattFg":"","sy51shtmRcomYn":"","abeekSustLsnFgNm":"","sy11shtmRcomYn":"","abeekTheoPntCnt":null,"sy31shtmRcomYn":"","submattFgNm":"기초과목","sbjtCd":"CHEM113","subTheoTotalPnt":null,"mjCd":"DS03008002001","sy61shtmRcomYn":"","sy22shtmRcomYn":"","mjCdNm":"의학전공(과)","sustLsnFg":"U0208002","sy52shtmRcomYn":"","sy21shtmRcomYn":"","sbjtChgFgNm":"","abeekDgnPntCnt":null,"sbjtKorNm":"화학2","sy41shtmRcomYn":"","genrl1stgNeceGrp":"C","abeekGrpChoice":"","abeekSubmattFg":"","theoFgNm":"이론","abeekDetaSubmattFgNm":"","sy32shtmRcomYn":"","openTm":3.0,"pnt":3.0,"sbjtId":"992","abeekChoiceSbjtCnt":null,"corsYy":"2019","subInspTotalPnt":null,"abeekGrpNm":"","rowStatus":1,"theoFg":"U0210001","curiNo":"2019106234"},{"submattFg":"U0209003","stgNeceGrpNm":"택B2","sideTotalPnt":1.0,"sbjtChgFg":"","subDgnTotalPnt":null,"sy62shtmRcomYn":"","abeekSubmattFgNm":"","sustLsnFgNm":"교필","sy12shtmRcomYn":"","sy42shtmRcomYn":"","abeekInspPracPntCnt":null,"genrl1stgNeceSbjtCnt":2.0,"abeekSustLsnFg":"","abeekDetaSubmattFg":"","sy51shtmRcomYn":"","abeekSustLsnFgNm":"","sy11shtmRcomYn":"○","abeekTheoPntCnt":null,"sy31shtmRcomYn":"","submattFgNm":"기초과목","sbjtCd":"CHEM115","subTheoTotalPnt":null,"mjCd":"DS03008002001","sy61shtmRcomYn":"","sy22shtmRcomYn":"","mjCdNm":"의학전공(과)","sustLsnFg":"U0208002","sy52shtmRcomYn":"","sy21shtmRcomYn":"","sbjtChgFgNm":"","abeekDgnPntCnt":null,"sbjtKorNm":"화학실험1","sy41shtmRcomYn":"","genrl1stgNeceGrp":"B","abeekGrpChoice":"","abeekSubmattFg":"","theoFgNm":"실습","abeekDetaSubmattFgNm":"","sy32shtmRcomYn":"","openTm":2.0,"pnt":1.0,"sbjtId":"1002","abeekChoiceSbjtCnt":null,"corsYy":"2019","subInspTotalPnt":null,"abeekGrpNm":"","rowStatus":1,"theoFg":"U0210002","curiNo":"2019106235"},{"submattFg":"U0209003","stgNeceGrpNm":"택C2","sideTotalPnt":1.0,"sbjtChgFg":"","subDgnTotalPnt":null,"sy62shtmRcomYn":"","abeekSubmattFgNm":"","sustLsnFgNm":"교필","sy12shtmRcomYn":"○","sy42shtmRcomYn":"","abeekInspPracPntCnt":null,"genrl1stgNeceSbjtCnt":2.0,"abeekSustLsnFg":"","abeekDetaSubmattFg":"","sy51shtmRcomYn":"","abeekSustLsnFgNm":"","sy11shtmRcomYn":"","abeekTheoPntCnt":null,"sy31shtmRcomYn":"","submattFgNm":"기초과목","sbjtCd":"CHEM116","subTheoTotalPnt":null,"mjCd":"DS03008002001","sy61shtmRcomYn":"","sy22shtmRcomYn":"","mjCdNm":"의학전공(과)","sustLsnFg":"U0208002","sy52shtmRcomYn":"","sy21shtmRcomYn":"","sbjtChgFgNm":"","abeekDgnPntCnt":null,"sbjtKorNm":"화학실험2","sy41shtmRcomYn":"","genrl1stgNeceGrp":"C","abeekGrpChoice":"","abeekSubmattFg":"","theoFgNm":"실습","abeekDetaSubmattFgNm":"","sy32shtmRcomYn":"","openTm":2.0,"pnt":1.0,"sbjtId":"1003","abeekChoiceSbjtCnt":null,"corsYy":"2019","subInspTotalPnt":null,"abeekGrpNm":"","rowStatus":1,"theoFg":"U0210002","curiNo":"2019106236"},{"submattFg":"U0209003","stgNeceGrpNm":"","sideTotalPnt":3.0,"sbjtChgFg":"","subDgnTotalPnt":null,"sy62shtmRcomYn":"","abeekSubmattFgNm":"","sustLsnFgNm":"교필","sy12shtmRcomYn":"","sy42shtmRcomYn":"","abeekInspPracPntCnt":null,"genrl1stgNeceSbjtCnt":null,"abeekSustLsnFg":"","abeekDetaSubmattFg":"","sy51shtmRcomYn":"","abeekSustLsnFgNm":"","sy11shtmRcomYn":"","abeekTheoPntCnt":null,"sy31shtmRcomYn":"","submattFgNm":"기초과목","sbjtCd":"CHEM211","subTheoTotalPnt":null,"mjCd":"DS03008002001","sy61shtmRcomYn":"","sy22shtmRcomYn":"","mjCdNm":"의학전공(과)","sustLsnFg":"U0208002","sy52shtmRcomYn":"","sy21shtmRcomYn":"○","sbjtChgFgNm":"","abeekDgnPntCnt":null,"sbjtKorNm":"유기화학","sy41shtmRcomYn":"","genrl1stgNeceGrp":"","abeekGrpChoice":"","abeekSubmattFg":"","theoFgNm":"이론","abeekDetaSubmattFgNm":"","sy32shtmRcomYn":"","openTm":3.0,"pnt":3.0,"sbjtId":"643","abeekChoiceSbjtCnt":null,"corsYy":"2019","subInspTotalPnt":null,"abeekGrpNm":"","rowStatus":1,"theoFg":"U0210001","curiNo":"2019106237"},{"submattFg":"U0209003","stgNeceGrpNm":"","sideTotalPnt":1.0,"sbjtChgFg":"","subDgnTotalPnt":null,"sy62shtmRcomYn":"","abeekSubmattFgNm":"","sustLsnFgNm":"교필","sy12shtmRcomYn":"","sy42shtmRcomYn":"","abeekInspPracPntCnt":null,"genrl1stgNeceSbjtCnt":null,"abeekSustLsnFg":"","abeekDetaSubmattFg":"","sy51shtmRcomYn":"","abeekSustLsnFgNm":"","sy11shtmRcomYn":"","abeekTheoPntCnt":null,"sy31shtmRcomYn":"","submattFgNm":"기초과목","sbjtCd":"CPE201","subTheoTotalPnt":null,"mjCd":"DS03008002001","sy61shtmRcomYn":"","sy22shtmRcomYn":"○","mjCdNm":"의학전공(과)","sustLsnFg":"U0208002","sy52shtmRcomYn":"","sy21shtmRcomYn":"","sbjtChgFgNm":"","abeekDgnPntCnt":null,"sbjtKorNm":"체육-호신술","sy41shtmRcomYn":"","genrl1stgNeceGrp":"","abeekGrpChoice":"","abeekSubmattFg":"","theoFgNm":"","abeekDetaSubmattFgNm":"","sy32shtmRcomYn":"","openTm":2.0,"pnt":1.0,"sbjtId":"20170566","abeekChoiceSbjtCnt":null,"corsYy":"2019","subInspTotalPnt":null,"abeekGrpNm":"","rowStatus":1,"theoFg":"","curiNo":"2019106238"},{"submattFg":"U0209003","stgNeceGrpNm":"택A1","sideTotalPnt":3.0,"sbjtChgFg":"","subDgnTotalPnt":null,"sy62shtmRcomYn":"","abeekSubmattFgNm":"","sustLsnFgNm":"교필","sy12shtmRcomYn":"","sy42shtmRcomYn":"","abeekInspPracPntCnt":null,"genrl1stgNeceSbjtCnt":1.0,"abeekSustLsnFg":"","abeekDetaSubmattFg":"","sy51shtmRcomYn":"","abeekSustLsnFgNm":"","sy11shtmRcomYn":"○","abeekTheoPntCnt":null,"sy31shtmRcomYn":"","submattFgNm":"기초과목","sbjtCd":"MATH102","subTheoTotalPnt":null,"mjCd":"DS03008002001","sy61shtmRcomYn":"","sy22shtmRcomYn":"","mjCdNm":"의학전공(과)","sustLsnFg":"U0208002","sy52shtmRcomYn":"","sy21shtmRcomYn":"","sbjtChgFgNm":"","abeekDgnPntCnt":null,"sbjtKorNm":"수학1","sy41shtmRcomYn":"","genrl1stgNeceGrp":"A","abeekGrpChoice":"","abeekSubmattFg":"","theoFgNm":"이론","abeekDetaSubmattFgNm":"","sy32shtmRcomYn":"","openTm":3.0,"pnt":3.0,"sbjtId":"527","abeekChoiceSbjtCnt":null,"corsYy":"2019","subInspTotalPnt":null,"abeekGrpNm":"","rowStatus":1,"theoFg":"U0210001","curiNo":"2019106239"},{"submattFg":"U0209003","stgNeceGrpNm":"","sideTotalPnt":3.0,"sbjtChgFg":"","subDgnTotalPnt":null,"sy62shtmRcomYn":"","abeekSubmattFgNm":"","sustLsnFgNm":"교필","sy12shtmRcomYn":"○","sy42shtmRcomYn":"","abeekInspPracPntCnt":null,"genrl1stgNeceSbjtCnt":null,"abeekSustLsnFg":"","abeekDetaSubmattFg":"","sy51shtmRcomYn":"","abeekSustLsnFgNm":"","sy11shtmRcomYn":"","abeekTheoPntCnt":null,"sy31shtmRcomYn":"","submattFgNm":"기초과목","sbjtCd":"MATH103","subTheoTotalPnt":null,"mjCd":"DS03008002001","sy61shtmRcomYn":"","sy22shtmRcomYn":"","mjCdNm":"의학전공(과)","sustLsnFg":"U0208002","sy52shtmRcomYn":"","sy21shtmRcomYn":"","sbjtChgFgNm":"","abeekDgnPntCnt":null,"sbjtKorNm":"수학2","sy41shtmRcomYn":"","genrl1stgNeceGrp":"","abeekGrpChoice":"","abeekSubmattFg":"","theoFgNm":"이론","abeekDetaSubmattFgNm":"","sy32shtmRcomYn":"","openTm":3.0,"pnt":3.0,"sbjtId":"528","abeekChoiceSbjtCnt":null,"corsYy":"2019","subInspTotalPnt":null,"abeekGrpNm":"","rowStatus":1,"theoFg":"U0210001","curiNo":"2019106240"},{"submattFg":"U0209003","stgNeceGrpNm":"","sideTotalPnt":1.0,"sbjtChgFg":"","subDgnTotalPnt":null,"sy62shtmRcomYn":"","abeekSubmattFgNm":"","sustLsnFgNm":"교필","sy12shtmRcomYn":"○","sy42shtmRcomYn":"","abeekInspPracPntCnt":null,"genrl1stgNeceSbjtCnt":null,"abeekSustLsnFg":"","abeekDetaSubmattFg":"","sy51shtmRcomYn":"","abeekSustLsnFgNm":"","sy11shtmRcomYn":"","abeekTheoPntCnt":null,"sy31shtmRcomYn":"","submattFgNm":"기초과목","sbjtCd":"MED103","subTheoTotalPnt":null,"mjCd":"DS03008002001","sy61shtmRcomYn":"","sy22shtmRcomYn":"","mjCdNm":"의학전공(과)","sustLsnFg":"U0208002","sy52shtmRcomYn":"","sy21shtmRcomYn":"","sbjtChgFgNm":"","abeekDgnPntCnt":null,"sbjtKorNm":"체육1(수영)","sy41shtmRcomYn":"","genrl1stgNeceGrp":"","abeekGrpChoice":"","abeekSubmattFg":"","theoFgNm":"실습","abeekDetaSubmattFgNm":"","sy32shtmRcomYn":"","openTm":2.0,"pnt":1.0,"sbjtId":"20160392","abeekChoiceSbjtCnt":null,"corsYy":"2019","subInspTotalPnt":null,"abeekGrpNm":"","rowStatus":1,"theoFg":"U0210002","curiNo":"2019106241"},{"submattFg":"U0209003","stgNeceGrpNm":"택A1","sideTotalPnt":3.0,"sbjtChgFg":"","subDgnTotalPnt":null,"sy62shtmRcomYn":"","abeekSubmattFgNm":"","sustLsnFgNm":"교필","sy12shtmRcomYn":"","sy42shtmRcomYn":"","abeekInspPracPntCnt":null,"genrl1stgNeceSbjtCnt":1.0,"abeekSustLsnFg":"","abeekDetaSubmattFg":"","sy51shtmRcomYn":"","abeekSustLsnFgNm":"","sy11shtmRcomYn":"○","abeekTheoPntCnt":null,"sy31shtmRcomYn":"","submattFgNm":"기초과목","sbjtCd":"PHYS117","subTheoTotalPnt":null,"mjCd":"DS03008002001","sy61shtmRcomYn":"","sy22shtmRcomYn":"","mjCdNm":"의학전공(과)","sustLsnFg":"U0208002","sy52shtmRcomYn":"","sy21shtmRcomYn":"","sbjtChgFgNm":"","abeekDgnPntCnt":null,"sbjtKorNm":"물리학","sy41shtmRcomYn":"","genrl1stgNeceGrp":"A","abeekGrpChoice":"","abeekSubmattFg":"","theoFgNm":"이론","abeekDetaSubmattFgNm":"","sy32shtmRcomYn":"","openTm":3.0,"pnt":3.0,"sbjtId":"11813","abeekChoiceSbjtCnt":null,"corsYy":"2019","subInspTotalPnt":null,"abeekGrpNm":"","rowStatus":1,"theoFg":"U0210001","curiNo":"2019106242"},{"submattFg":"U0209003","stgNeceGrpNm":"","sideTotalPnt":3.0,"sbjtChgFg":"","subDgnTotalPnt":null,"sy62shtmRcomYn":"","abeekSubmattFgNm":"","sustLsnFgNm":"교선","sy12shtmRcomYn":"○","sy42shtmRcomYn":"","abeekInspPracPntCnt":null,"genrl1stgNeceSbjtCnt":null,"abeekSustLsnFg":"","abeekDetaSubmattFg":"","sy51shtmRcomYn":"","abeekSustLsnFgNm":"","sy11shtmRcomYn":"","abeekTheoPntCnt":null,"sy31shtmRcomYn":"","submattFgNm":"기초과목","sbjtCd":"CMP102","subTheoTotalPnt":null,"mjCd":"DS03008002001","sy61shtmRcomYn":"","sy22shtmRcomYn":"","mjCdNm":"의학전공(과)","sustLsnFg":"U0208003","sy52shtmRcomYn":"","sy21shtmRcomYn":"","sbjtChgFgNm":"","abeekDgnPntCnt":null,"sbjtKorNm":"웹 저작 기초","sy41shtmRcomYn":"","genrl1stgNeceGrp":"","abeekGrpChoice":"","abeekSubmattFg":"","theoFgNm":"이론+실습","abeekDetaSubmattFgNm":"","sy32shtmRcomYn":"","openTm":4.0,"pnt":3.0,"sbjtId":"10367","abeekChoiceSbjtCnt":null,"corsYy":"2019","subInspTotalPnt":null,"abeekGrpNm":"","rowStatus":1,"theoFg":"U0210005","curiNo":"2019106244"},{"submattFg":"U0209001","stgNeceGrpNm":"","sideTotalPnt":6.0,"sbjtChgFg":"","subDgnTotalPnt":null,"sy62shtmRcomYn":"","abeekSubmattFgNm":"","sustLsnFgNm":"전필","sy12shtmRcomYn":"","sy42shtmRcomYn":"","abeekInspPracPntCnt":null,"genrl1stgNeceSbjtCnt":null,"abeekSustLsnFg":"U0225001","abeekDetaSubmattFg":"","sy51shtmRcomYn":"","abeekSustLsnFgNm":"인필","sy11shtmRcomYn":"","abeekTheoPntCnt":null,"sy31shtmRcomYn":"○","submattFgNm":"전공과목","sbjtCd":"MED3013","subTheoTotalPnt":null,"mjCd":"DS03008002001","sy61shtmRcomYn":"","sy22shtmRcomYn":"","mjCdNm":"의학전공(과)","sustLsnFg":"U0208004","sy52shtmRcomYn":"","sy21shtmRcomYn":"","sbjtChgFgNm":"","abeekDgnPntCnt":null,"sbjtKorNm":"몸의구조 1","sy41shtmRcomYn":"","genrl1stgNeceGrp":"","abeekGrpChoice":"","abeekSubmattFg":"","theoFgNm":"이론","abeekDetaSubmattFgNm":"","sy32shtmRcomYn":"","openTm":null,"pnt":6.0,"sbjtId":"20120870","abeekChoiceSbjtCnt":null,"corsYy":"2019","subInspTotalPnt":null,"abeekGrpNm":"","rowStatus":1,"theoFg":"U0210001","curiNo":"2019106204"},{"submattFg":"U0209001","stgNeceGrpNm":"","sideTotalPnt":2.0,"sbjtChgFg":"","subDgnTotalPnt":null,"sy62shtmRcomYn":"○","abeekSubmattFgNm":"","sustLsnFgNm":"전필","sy12shtmRcomYn":"","sy42shtmRcomYn":"","abeekInspPracPntCnt":null,"genrl1stgNeceSbjtCnt":null,"abeekSustLsnFg":"","abeekDetaSubmattFg":"","sy51shtmRcomYn":"","abeekSustLsnFgNm":"","sy11shtmRcomYn":"","abeekTheoPntCnt":null,"sy31shtmRcomYn":"","submattFgNm":"전공과목","sbjtCd":"10814","subTheoTotalPnt":null,"mjCd":"DS03008002001","sy61shtmRcomYn":"○","sy22shtmRcomYn":"","mjCdNm":"의학전공(과)","sustLsnFg":"U0208004","sy52shtmRcomYn":"","sy21shtmRcomYn":"","sbjtChgFgNm":"","abeekDgnPntCnt":null,"sbjtKorNm":"진단검사의학실습","sy41shtmRcomYn":"","genrl1stgNeceGrp":"","abeekGrpChoice":"","abeekSubmattFg":"","theoFgNm":"실습","abeekDetaSubmattFgNm":"","sy32shtmRcomYn":"","openTm":null,"pnt":2.0,"sbjtId":"10814","abeekChoiceSbjtCnt":null,"corsYy":"2019","subInspTotalPnt":null,"abeekGrpNm":"","rowStatus":1,"theoFg":"U0210002","curiNo":"2019106162"},{"submattFg":"U0209001","stgNeceGrpNm":"","sideTotalPnt":2.0,"sbjtChgFg":"","subDgnTotalPnt":null,"sy62shtmRcomYn":"","abeekSubmattFgNm":"","sustLsnFgNm":"전필","sy12shtmRcomYn":"","sy42shtmRcomYn":"","abeekInspPracPntCnt":null,"genrl1stgNeceSbjtCnt":null,"abeekSustLsnFg":"","abeekDetaSubmattFg":"","sy51shtmRcomYn":"","abeekSustLsnFgNm":"","sy11shtmRcomYn":"","abeekTheoPntCnt":null,"sy31shtmRcomYn":"","submattFgNm":"전공과목","sbjtCd":"10815","subTheoTotalPnt":null,"mjCd":"DS03008002001","sy61shtmRcomYn":"","sy22shtmRcomYn":"","mjCdNm":"의학전공(과)","sustLsnFg":"U0208004","sy52shtmRcomYn":"","sy21shtmRcomYn":"","sbjtChgFgNm":"","abeekDgnPntCnt":null,"sbjtKorNm":"마취통증의학실습","sy41shtmRcomYn":"","genrl1stgNeceGrp":"","abeekGrpChoice":"","abeekSubmattFg":"","theoFgNm":"실습","abeekDetaSubmattFgNm":"","sy32shtmRcomYn":"","openTm":2.0,"pnt":2.0,"sbjtId":"10815","abeekChoiceSbjtCnt":null,"corsYy":"2019","subInspTotalPnt":null,"abeekGrpNm":"","rowStatus":1,"theoFg":"U0210002","curiNo":"2019106163"},{"submattFg":"U0209001","stgNeceGrpNm":"","sideTotalPnt":1.0,"sbjtChgFg":"","subDgnTotalPnt":null,"sy62shtmRcomYn":"○","abeekSubmattFgNm":"","sustLsnFgNm":"전필","sy12shtmRcomYn":"","sy42shtmRcomYn":"","abeekInspPracPntCnt":null,"genrl1stgNeceSbjtCnt":null,"abeekSustLsnFg":"","abeekDetaSubmattFg":"","sy51shtmRcomYn":"","abeekSustLsnFgNm":"","sy11shtmRcomYn":"","abeekTheoPntCnt":null,"sy31shtmRcomYn":"","submattFgNm":"전공과목","sbjtCd":"1101","subTheoTotalPnt":null,"mjCd":"DS03008002001","sy61shtmRcomYn":"○","sy22shtmRcomYn":"","mjCdNm":"의학전공(과)","sustLsnFg":"U0208004","sy52shtmRcomYn":"","sy21shtmRcomYn":"","sbjtChgFgNm":"","abeekDgnPntCnt":null,"sbjtKorNm":"법의학","sy41shtmRcomYn":"","genrl1stgNeceGrp":"","abeekGrpChoice":"","abeekSubmattFg":"","theoFgNm":"이론","abeekDetaSubmattFgNm":"","sy32shtmRcomYn":"","openTm":1.0,"pnt":1.0,"sbjtId":"1101","abeekChoiceSbjtCnt":null,"corsYy":"2019","subInspTotalPnt":null,"abeekGrpNm":"","rowStatus":1,"theoFg":"U0210001","curiNo":"2019106164"},{"submattFg":"U0209001","stgNeceGrpNm":"","sideTotalPnt":2.0,"sbjtChgFg":"","subDgnTotalPnt":null,"sy62shtmRcomYn":"○","abeekSubmattFgNm":"","sustLsnFgNm":"전필","sy12shtmRcomYn":"","sy42shtmRcomYn":"","abeekInspPracPntCnt":null,"genrl1stgNeceSbjtCnt":null,"abeekSustLsnFg":"","abeekDetaSubmattFg":"","sy51shtmRcomYn":"","abeekSustLsnFgNm":"","sy11shtmRcomYn":"","abeekTheoPntCnt":null,"sy31shtmRcomYn":"","submattFgNm":"전공과목","sbjtCd":"1111","subTheoTotalPnt":null,"mjCd":"DS03008002001","sy61shtmRcomYn":"○","sy22shtmRcomYn":"","mjCdNm":"의학전공(과)","sustLsnFg":"U0208004","sy52shtmRcomYn":"","sy21shtmRcomYn":"","sbjtChgFgNm":"","abeekDgnPntCnt":null,"sbjtKorNm":"신경과학실습","sy41shtmRcomYn":"","genrl1stgNeceGrp":"","abeekGrpChoice":"","abeekSubmattFg":"","theoFgNm":"실습","abeekDetaSubmattFgNm":"","sy32shtmRcomYn":"","openTm":null,"pnt":2.0,"sbjtId":"1111","abeekChoiceSbjtCnt":null,"corsYy":"2019","subInspTotalPnt":null,"abeekGrpNm":"","rowStatus":1,"theoFg":"U0210002","curiNo":"2019106165"},{"submattFg":"U0209001","stgNeceGrpNm":"","sideTotalPnt":2.0,"sbjtChgFg":"","subDgnTotalPnt":null,"sy62shtmRcomYn":"○","abeekSubmattFgNm":"","sustLsnFgNm":"전필","sy12shtmRcomYn":"","sy42shtmRcomYn":"","abeekInspPracPntCnt":null,"genrl1stgNeceSbjtCnt":null,"abeekSustLsnFg":"","abeekDetaSubmattFg":"","sy51shtmRcomYn":"","abeekSustLsnFgNm":"","sy11shtmRcomYn":"","abeekTheoPntCnt":null,"sy31shtmRcomYn":"","submattFgNm":"전공과목","sbjtCd":"1112","subTheoTotalPnt":null,"mjCd":"DS03008002001","sy61shtmRcomYn":"○","sy22shtmRcomYn":"","mjCdNm":"의학전공(과)","sustLsnFg":"U0208004","sy52shtmRcomYn":"","sy21shtmRcomYn":"","sbjtChgFgNm":"","abeekDgnPntCnt":null,"sbjtKorNm":"신경외과학실습","sy41shtmRcomYn":"","genrl1stgNeceGrp":"","abeekGrpChoice":"","abeekSubmattFg":"","theoFgNm":"실습","abeekDetaSubmattFgNm":"","sy32shtmRcomYn":"","openTm":1.0,"pnt":2.0,"sbjtId":"1112","abeekChoiceSbjtCnt":null,"corsYy":"2019","subInspTotalPnt":null,"abeekGrpNm":"","rowStatus":1,"theoFg":"U0210002","curiNo":"2019106166"},{"submattFg":"U0209001","stgNeceGrpNm":"","sideTotalPnt":2.0,"sbjtChgFg":"","subDgnTotalPnt":null,"sy62shtmRcomYn":"○","abeekSubmattFgNm":"","sustLsnFgNm":"전필","sy12shtmRcomYn":"","sy42shtmRcomYn":"","abeekInspPracPntCnt":null,"genrl1stgNeceSbjtCnt":null,"abeekSustLsnFg":"","abeekDetaSubmattFg":"","sy51shtmRcomYn":"","abeekSustLsnFgNm":"","sy11shtmRcomYn":"","abeekTheoPntCnt":null,"sy31shtmRcomYn":"","submattFgNm":"전공과목","sbjtCd":"1113","subTheoTotalPnt":null,"mjCd":"DS03008002001","sy61shtmRcomYn":"○","sy22shtmRcomYn":"","mjCdNm":"의학전공(과)","sustLsnFg":"U0208004","sy52shtmRcomYn":"","sy21shtmRcomYn":"","sbjtChgFgNm":"","abeekDgnPntCnt":null,"sbjtKorNm":"정형외과학실습","sy41shtmRcomYn":"","genrl1stgNeceGrp":"","abeekGrpChoice":"","abeekSubmattFg":"","theoFgNm":"실습","abeekDetaSubmattFgNm":"","sy32shtmRcomYn":"","openTm":null,"pnt":2.0,"sbjtId":"1113","abeekChoiceSbjtCnt":null,"corsYy":"2019","subInspTotalPnt":null,"abeekGrpNm":"","rowStatus":1,"theoFg":"U0210002","curiNo":"2019106167"},{"submattFg":"U0209001","stgNeceGrpNm":"","sideTotalPnt":2.0,"sbjtChgFg":"","subDgnTotalPnt":null,"sy62shtmRcomYn":"○","abeekSubmattFgNm":"","sustLsnFgNm":"전필","sy12shtmRcomYn":"","sy42shtmRcomYn":"","abeekInspPracPntCnt":null,"genrl1stgNeceSbjtCnt":null,"abeekSustLsnFg":"","abeekDetaSubmattFg":"","sy51shtmRcomYn":"","abeekSustLsnFgNm":"","sy11shtmRcomYn":"","abeekTheoPntCnt":null,"sy31shtmRcomYn":"","submattFgNm":"전공과목","sbjtCd":"1115","subTheoTotalPnt":null,"mjCd":"DS03008002001","sy61shtmRcomYn":"○","sy22shtmRcomYn":"","mjCdNm":"의학전공(과)","sustLsnFg":"U0208004","sy52shtmRcomYn":"","sy21shtmRcomYn":"","sbjtChgFgNm":"","abeekDgnPntCnt":null,"sbjtKorNm":"성형외과학실습","sy41shtmRcomYn":"","genrl1stgNeceGrp":"","abeekGrpChoice":"","abeekSubmattFg":"","theoFgNm":"실습","abeekDetaSubmattFgNm":"","sy32shtmRcomYn":"","openTm":null,"pnt":2.0,"sbjtId":"1115","abeekChoiceSbjtCnt":null,"corsYy":"2019","subInspTotalPnt":null,"abeekGrpNm":"","rowStatus":1,"theoFg":"U0210002","curiNo":"2019106168"},{"submattFg":"U0209001","stgNeceGrpNm":"","sideTotalPnt":2.0,"sbjtChgFg":"","subDgnTotalPnt":null,"sy62shtmRcomYn":"○","abeekSubmattFgNm":"","sustLsnFgNm":"전필","sy12shtmRcomYn":"","sy42shtmRcomYn":"","abeekInspPracPntCnt":null,"genrl1stgNeceSbjtCnt":null,"abeekSustLsnFg":"","abeekDetaSubmattFg":"","sy51shtmRcomYn":"","abeekSustLsnFgNm":"","sy11shtmRcomYn":"","abeekTheoPntCnt":null,"sy31shtmRcomYn":"","submattFgNm":"전공과목","sbjtCd":"1116","subTheoTotalPnt":null,"mjCd":"DS03008002001","sy61shtmRcomYn":"○","sy22shtmRcomYn":"","mjCdNm":"의학전공(과)","sustLsnFg":"U0208004","sy52shtmRcomYn":"","sy21shtmRcomYn":"","sbjtChgFgNm":"","abeekDgnPntCnt":null,"sbjtKorNm":"흉부외과학실습","sy41shtmRcomYn":"","genrl1stgNeceGrp":"","abeekGrpChoice":"","abeekSubmattFg":"","theoFgNm":"실습","abeekDetaSubmattFgNm":"","sy32shtmRcomYn":"","openTm":null,"pnt":2.0,"sbjtId":"1116","abeekChoiceSbjtCnt":null,"corsYy":"2019","subInspTotalPnt":null,"abeekGrpNm":"","rowStatus":1,"theoFg":"U0210002","curiNo":"2019106169"},{"submattFg":"U0209001","stgNeceGrpNm":"","sideTotalPnt":2.0,"sbjtChgFg":"","subDgnTotalPnt":null,"sy62shtmRcomYn":"○","abeekSubmattFgNm":"","sustLsnFgNm":"전필","sy12shtmRcomYn":"","sy42shtmRcomYn":"","abeekInspPracPntCnt":null,"genrl1stgNeceSbjtCnt":null,"abeekSustLsnFg":"","abeekDetaSubmattFg":"","sy51shtmRcomYn":"","abeekSustLsnFgNm":"","sy11shtmRcomYn":"","abeekTheoPntCnt":null,"sy31shtmRcomYn":"","submattFgNm":"전공과목","sbjtCd":"1117","subTheoTotalPnt":null,"mjCd":"DS03008002001","sy61shtmRcomYn":"○","sy22shtmRcomYn":"","mjCdNm":"의학전공(과)","sustLsnFg":"U0208004","sy52shtmRcomYn":"","sy21shtmRcomYn":"","sbjtChgFgNm":"","abeekDgnPntCnt":null,"sbjtKorNm":"이비인후과학실습","sy41shtmRcomYn":"","genrl1stgNeceGrp":"","abeekGrpChoice":"","abeekSubmattFg":"","theoFgNm":"실습","abeekDetaSubmattFgNm":"","sy32shtmRcomYn":"","openTm":null,"pnt":2.0,"sbjtId":"1117","abeekChoiceSbjtCnt":null,"corsYy":"2019","subInspTotalPnt":null,"abeekGrpNm":"","rowStatus":1,"theoFg":"U0210002","curiNo":"2019106170"},{"submattFg":"U0209001","stgNeceGrpNm":"","sideTotalPnt":2.0,"sbjtChgFg":"","subDgnTotalPnt":null,"sy62shtmRcomYn":"○","abeekSubmattFgNm":"","sustLsnFgNm":"전필","sy12shtmRcomYn":"","sy42shtmRcomYn":"","abeekInspPracPntCnt":null,"genrl1stgNeceSbjtCnt":null,"abeekSustLsnFg":"","abeekDetaSubmattFg":"","sy51shtmRcomYn":"","abeekSustLsnFgNm":"","sy11shtmRcomYn":"","abeekTheoPntCnt":null,"sy31shtmRcomYn":"","submattFgNm":"전공과목","sbjtCd":"1118","subTheoTotalPnt":null,"mjCd":"DS03008002001","sy61shtmRcomYn":"○","sy22shtmRcomYn":"","mjCdNm":"의학전공(과)","sustLsnFg":"U0208004","sy52shtmRcomYn":"","sy21shtmRcomYn":"","sbjtChgFgNm":"","abeekDgnPntCnt":null,"sbjtKorNm":"안과학실습","sy41shtmRcomYn":"","genrl1stgNeceGrp":"","abeekGrpChoice":"","abeekSubmattFg":"","theoFgNm":"실습","abeekDetaSubmattFgNm":"","sy32shtmRcomYn":"","openTm":null,"pnt":2.0,"sbjtId":"1118","abeekChoiceSbjtCnt":null,"corsYy":"2019","subInspTotalPnt":null,"abeekGrpNm":"","rowStatus":1,"theoFg":"U0210002","curiNo":"2019106171"},{"submattFg":"U0209001","stgNeceGrpNm":"","sideTotalPnt":2.0,"sbjtChgFg":"","subDgnTotalPnt":null,"sy62shtmRcomYn":"○","abeekSubmattFgNm":"","sustLsnFgNm":"전필","sy12shtmRcomYn":"","sy42shtmRcomYn":"","abeekInspPracPntCnt":null,"genrl1stgNeceSbjtCnt":null,"abeekSustLsnFg":"","abeekDetaSubmattFg":"","sy51shtmRcomYn":"","abeekSustLsnFgNm":"","sy11shtmRcomYn":"","abeekTheoPntCnt":null,"sy31shtmRcomYn":"","submattFgNm":"전공과목","sbjtCd":"1119","subTheoTotalPnt":null,"mjCd":"DS03008002001","sy61shtmRcomYn":"○","sy22shtmRcomYn":"","mjCdNm":"의학전공(과)","sustLsnFg":"U0208004","sy52shtmRcomYn":"","sy21shtmRcomYn":"","sbjtChgFgNm":"","abeekDgnPntCnt":null,"sbjtKorNm":"피부과학실습","sy41shtmRcomYn":"","genrl1stgNeceGrp":"","abeekGrpChoice":"","abeekSubmattFg":"","theoFgNm":"실습","abeekDetaSubmattFgNm":"","sy32shtmRcomYn":"","openTm":null,"pnt":2.0,"sbjtId":"1119","abeekChoiceSbjtCnt":null,"corsYy":"2019","subInspTotalPnt":null,"abeekGrpNm":"","rowStatus":1,"theoFg":"U0210002","curiNo":"2019106172"},{"submattFg":"U0209001","stgNeceGrpNm":"","sideTotalPnt":2.0,"sbjtChgFg":"","subDgnTotalPnt":null,"sy62shtmRcomYn":"○","abeekSubmattFgNm":"","sustLsnFgNm":"전필","sy12shtmRcomYn":"","sy42shtmRcomYn":"","abeekInspPracPntCnt":null,"genrl1stgNeceSbjtCnt":null,"abeekSustLsnFg":"","abeekDetaSubmattFg":"","sy51shtmRcomYn":"","abeekSustLsnFgNm":"","sy11shtmRcomYn":"","abeekTheoPntCnt":null,"sy31shtmRcomYn":"","submattFgNm":"전공과목","sbjtCd":"1120","subTheoTotalPnt":null,"mjCd":"DS03008002001","sy61shtmRcomYn":"○","sy22shtmRcomYn":"","mjCdNm":"의학전공(과)","sustLsnFg":"U0208004","sy52shtmRcomYn":"","sy21shtmRcomYn":"","sbjtChgFgNm":"","abeekDgnPntCnt":null,"sbjtKorNm":"비뇨기과학실습","sy41shtmRcomYn":"","genrl1stgNeceGrp":"","abeekGrpChoice":"","abeekSubmattFg":"","theoFgNm":"실습","abeekDetaSubmattFgNm":"","sy32shtmRcomYn":"","openTm":null,"pnt":2.0,"sbjtId":"1120","abeekChoiceSbjtCnt":null,"corsYy":"2019","subInspTotalPnt":null,"abeekGrpNm":"","rowStatus":1,"theoFg":"U0210002","curiNo":"2019106173"},{"submattFg":"U0209001","stgNeceGrpNm":"","sideTotalPnt":2.0,"sbjtChgFg":"","subDgnTotalPnt":null,"sy62shtmRcomYn":"○","abeekSubmattFgNm":"","sustLsnFgNm":"전필","sy12shtmRcomYn":"","sy42shtmRcomYn":"","abeekInspPracPntCnt":null,"genrl1stgNeceSbjtCnt":null,"abeekSustLsnFg":"","abeekDetaSubmattFg":"","sy51shtmRcomYn":"","abeekSustLsnFgNm":"","sy11shtmRcomYn":"","abeekTheoPntCnt":null,"sy31shtmRcomYn":"","submattFgNm":"전공과목","sbjtCd":"1122","subTheoTotalPnt":null,"mjCd":"DS03008002001","sy61shtmRcomYn":"○","sy22shtmRcomYn":"","mjCdNm":"의학전공(과)","sustLsnFg":"U0208004","sy52shtmRcomYn":"","sy21shtmRcomYn":"","sbjtChgFgNm":"","abeekDgnPntCnt":null,"sbjtKorNm":"재활의학실습","sy41shtmRcomYn":"","genrl1stgNeceGrp":"","abeekGrpChoice":"","abeekSubmattFg":"","theoFgNm":"실습","abeekDetaSubmattFgNm":"","sy32shtmRcomYn":"","openTm":null,"pnt":2.0,"sbjtId":"1122","abeekChoiceSbjtCnt":null,"corsYy":"2019","subInspTotalPnt":null,"abeekGrpNm":"","rowStatus":1,"theoFg":"U0210002","curiNo":"2019106174"},{"submattFg":"U0209001","stgNeceGrpNm":"","sideTotalPnt":2.0,"sbjtChgFg":"","subDgnTotalPnt":null,"sy62shtmRcomYn":"○","abeekSubmattFgNm":"","sustLsnFgNm":"전필","sy12shtmRcomYn":"","sy42shtmRcomYn":"","abeekInspPracPntCnt":null,"genrl1stgNeceSbjtCnt":null,"abeekSustLsnFg":"","abeekDetaSubmattFg":"","sy51shtmRcomYn":"","abeekSustLsnFgNm":"","sy11shtmRcomYn":"","abeekTheoPntCnt":null,"sy31shtmRcomYn":"","submattFgNm":"전공과목","sbjtCd":"1123","subTheoTotalPnt":null,"mjCd":"DS03008002001","sy61shtmRcomYn":"○","sy22shtmRcomYn":"","mjCdNm":"의학전공(과)","sustLsnFg":"U0208004","sy52shtmRcomYn":"","sy21shtmRcomYn":"","sbjtChgFgNm":"","abeekDgnPntCnt":null,"sbjtKorNm":"응급의학실습","sy41shtmRcomYn":"","genrl1stgNeceGrp":"","abeekGrpChoice":"","abeekSubmattFg":"","theoFgNm":"실습","abeekDetaSubmattFgNm":"","sy32shtmRcomYn":"","openTm":null,"pnt":2.0,"sbjtId":"1123","abeekChoiceSbjtCnt":null,"corsYy":"2019","subInspTotalPnt":null,"abeekGrpNm":"","rowStatus":1,"theoFg":"U0210002","curiNo":"2019106175"},{"submattFg":"U0209001","stgNeceGrpNm":"","sideTotalPnt":4.0,"sbjtChgFg":"","subDgnTotalPnt":null,"sy62shtmRcomYn":"○","abeekSubmattFgNm":"","sustLsnFgNm":"전필","sy12shtmRcomYn":"","sy42shtmRcomYn":"","abeekInspPracPntCnt":null,"genrl1stgNeceSbjtCnt":null,"abeekSustLsnFg":"","abeekDetaSubmattFg":"","sy51shtmRcomYn":"","abeekSustLsnFgNm":"","sy11shtmRcomYn":"","abeekTheoPntCnt":null,"sy31shtmRcomYn":"","submattFgNm":"전공과목","sbjtCd":"1124","subTheoTotalPnt":null,"mjCd":"DS03008002001","sy61shtmRcomYn":"○","sy22shtmRcomYn":"","mjCdNm":"의학전공(과)","sustLsnFg":"U0208004","sy52shtmRcomYn":"","sy21shtmRcomYn":"","sbjtChgFgNm":"","abeekDgnPntCnt":null,"sbjtKorNm":"선택실습","sy41shtmRcomYn":"","genrl1stgNeceGrp":"","abeekGrpChoice":"","abeekSubmattFg":"","theoFgNm":"실습","abeekDetaSubmattFgNm":"","sy32shtmRcomYn":"","openTm":null,"pnt":4.0,"sbjtId":"1124","abeekChoiceSbjtCnt":null,"corsYy":"2019","subInspTotalPnt":null,"abeekGrpNm":"","rowStatus":1,"theoFg":"U0210002","curiNo":"2019106176"},{"submattFg":"U0209001","stgNeceGrpNm":"","sideTotalPnt":4.0,"sbjtChgFg":"","subDgnTotalPnt":null,"sy62shtmRcomYn":"","abeekSubmattFgNm":"","sustLsnFgNm":"전필","sy12shtmRcomYn":"","sy42shtmRcomYn":"","abeekInspPracPntCnt":null,"genrl1stgNeceSbjtCnt":null,"abeekSustLsnFg":"","abeekDetaSubmattFg":"","sy51shtmRcomYn":"○","abeekSustLsnFgNm":"","sy11shtmRcomYn":"","abeekTheoPntCnt":null,"sy31shtmRcomYn":"","submattFgNm":"전공과목","sbjtCd":"1129","subTheoTotalPnt":null,"mjCd":"DS03008002001","sy61shtmRcomYn":"","sy22shtmRcomYn":"","mjCdNm":"의학전공(과)","sustLsnFg":"U0208004","sy52shtmRcomYn":"○","sy21shtmRcomYn":"","sbjtChgFgNm":"","abeekDgnPntCnt":null,"sbjtKorNm":"산부인과학실습","sy41shtmRcomYn":"","genrl1stgNeceGrp":"","abeekGrpChoice":"","abeekSubmattFg":"","theoFgNm":"실습","abeekDetaSubmattFgNm":"","sy32shtmRcomYn":"","openTm":null,"pnt":4.0,"sbjtId":"1129","abeekChoiceSbjtCnt":null,"corsYy":"2019","subInspTotalPnt":null,"abeekGrpNm":"","rowStatus":1,"theoFg":"U0210002","curiNo":"2019106177"},{"submattFg":"U0209001","stgNeceGrpNm":"","sideTotalPnt":4.0,"sbjtChgFg":"","subDgnTotalPnt":null,"sy62shtmRcomYn":"○","abeekSubmattFgNm":"","sustLsnFgNm":"전필","sy12shtmRcomYn":"","sy42shtmRcomYn":"","abeekInspPracPntCnt":null,"genrl1stgNeceSbjtCnt":null,"abeekSustLsnFg":"","abeekDetaSubmattFg":"","sy51shtmRcomYn":"○","abeekSustLsnFgNm":"","sy11shtmRcomYn":"","abeekTheoPntCnt":null,"sy31shtmRcomYn":"","submattFgNm":"전공과목","sbjtCd":"1131","subTheoTotalPnt":null,"mjCd":"DS03008002001","sy61shtmRcomYn":"○","sy22shtmRcomYn":"","mjCdNm":"의학전공(과)","sustLsnFg":"U0208004","sy52shtmRcomYn":"○","sy21shtmRcomYn":"","sbjtChgFgNm":"","abeekDgnPntCnt":null,"sbjtKorNm":"정신과학실습","sy41shtmRcomYn":"","genrl1stgNeceGrp":"","abeekGrpChoice":"","abeekSubmattFg":"","theoFgNm":"실습","abeekDetaSubmattFgNm":"","sy32shtmRcomYn":"","openTm":null,"pnt":4.0,"sbjtId":"1131","abeekChoiceSbjtCnt":null,"corsYy":"2019","subInspTotalPnt":null,"abeekGrpNm":"","rowStatus":1,"theoFg":"U0210002","curiNo":"2019106178"},{"submattFg":"U0209001","stgNeceGrpNm":"","sideTotalPnt":4.0,"sbjtChgFg":"","subDgnTotalPnt":null,"sy62shtmRcomYn":"","abeekSubmattFgNm":"","sustLsnFgNm":"전필","sy12shtmRcomYn":"","sy42shtmRcomYn":"","abeekInspPracPntCnt":null,"genrl1stgNeceSbjtCnt":null,"abeekSustLsnFg":"","abeekDetaSubmattFg":"","sy51shtmRcomYn":"○","abeekSustLsnFgNm":"","sy11shtmRcomYn":"","abeekTheoPntCnt":null,"sy31shtmRcomYn":"","submattFgNm":"전공과목","sbjtCd":"11330","subTheoTotalPnt":null,"mjCd":"DS03008002001","sy61shtmRcomYn":"","sy22shtmRcomYn":"","mjCdNm":"의학전공(과)","sustLsnFg":"U0208004","sy52shtmRcomYn":"○","sy21shtmRcomYn":"","sbjtChgFgNm":"","abeekDgnPntCnt":null,"sbjtKorNm":"외과학실습","sy41shtmRcomYn":"","genrl1stgNeceGrp":"","abeekGrpChoice":"","abeekSubmattFg":"","theoFgNm":"실습","abeekDetaSubmattFgNm":"","sy32shtmRcomYn":"","openTm":null,"pnt":4.0,"sbjtId":"11330","abeekChoiceSbjtCnt":null,"corsYy":"2019","subInspTotalPnt":null,"abeekGrpNm":"","rowStatus":1,"theoFg":"U0210002","curiNo":"2019106179"},{"submattFg":"U0209001","stgNeceGrpNm":"","sideTotalPnt":2.0,"sbjtChgFg":"","subDgnTotalPnt":null,"sy62shtmRcomYn":"○","abeekSubmattFgNm":"","sustLsnFgNm":"전필","sy12shtmRcomYn":"","sy42shtmRcomYn":"","abeekInspPracPntCnt":null,"genrl1stgNeceSbjtCnt":null,"abeekSustLsnFg":"","abeekDetaSubmattFg":"","sy51shtmRcomYn":"","abeekSustLsnFgNm":"","sy11shtmRcomYn":"","abeekTheoPntCnt":null,"sy31shtmRcomYn":"","submattFgNm":"전공과목","sbjtCd":"1134","subTheoTotalPnt":null,"mjCd":"DS03008002001","sy61shtmRcomYn":"○","sy22shtmRcomYn":"","mjCdNm":"의학전공(과)","sustLsnFg":"U0208004","sy52shtmRcomYn":"","sy21shtmRcomYn":"","sbjtChgFgNm":"","abeekDgnPntCnt":null,"sbjtKorNm":"지역사회의학실습","sy41shtmRcomYn":"","genrl1stgNeceGrp":"","abeekGrpChoice":"","abeekSubmattFg":"","theoFgNm":"실습","abeekDetaSubmattFgNm":"","sy32shtmRcomYn":"","openTm":null,"pnt":2.0,"sbjtId":"1134","abeekChoiceSbjtCnt":null,"corsYy":"2019","subInspTotalPnt":null,"abeekGrpNm":"","rowStatus":1,"theoFg":"U0210002","curiNo":"2019106180"},{"submattFg":"U0209001","stgNeceGrpNm":"","sideTotalPnt":2.0,"sbjtChgFg":"","subDgnTotalPnt":null,"sy62shtmRcomYn":"○","abeekSubmattFgNm":"","sustLsnFgNm":"전필","sy12shtmRcomYn":"","sy42shtmRcomYn":"","abeekInspPracPntCnt":null,"genrl1stgNeceSbjtCnt":null,"abeekSustLsnFg":"","abeekDetaSubmattFg":"","sy51shtmRcomYn":"","abeekSustLsnFgNm":"","sy11shtmRcomYn":"","abeekTheoPntCnt":null,"sy31shtmRcomYn":"","submattFgNm":"전공과목","sbjtCd":"12919","subTheoTotalPnt":null,"mjCd":"DS03008002001","sy61shtmRcomYn":"○","sy22shtmRcomYn":"","mjCdNm":"의학전공(과)","sustLsnFg":"U0208004","sy52shtmRcomYn":"","sy21shtmRcomYn":"","sbjtChgFgNm":"","abeekDgnPntCnt":null,"sbjtKorNm":"방사선종양학실습","sy41shtmRcomYn":"","genrl1stgNeceGrp":"","abeekGrpChoice":"","abeekSubmattFg":"","theoFgNm":"실습","abeekDetaSubmattFgNm":"","sy32shtmRcomYn":"","openTm":2.0,"pnt":2.0,"sbjtId":"12919","abeekChoiceSbjtCnt":null,"corsYy":"2019","subInspTotalPnt":null,"abeekGrpNm":"","rowStatus":1,"theoFg":"U0210002","curiNo":"2019106181"},{"submattFg":"U0209001","stgNeceGrpNm":"","sideTotalPnt":2.0,"sbjtChgFg":"","subDgnTotalPnt":null,"sy62shtmRcomYn":"○","abeekSubmattFgNm":"","sustLsnFgNm":"전필","sy12shtmRcomYn":"","sy42shtmRcomYn":"","abeekInspPracPntCnt":null,"genrl1stgNeceSbjtCnt":null,"abeekSustLsnFg":"","abeekDetaSubmattFg":"","sy51shtmRcomYn":"","abeekSustLsnFgNm":"","sy11shtmRcomYn":"","abeekTheoPntCnt":null,"sy31shtmRcomYn":"","submattFgNm":"전공과목","sbjtCd":"14429","subTheoTotalPnt":null,"mjCd":"DS03008002001","sy61shtmRcomYn":"○","sy22shtmRcomYn":"","mjCdNm":"의학전공(과)","sustLsnFg":"U0208004","sy52shtmRcomYn":"","sy21shtmRcomYn":"","sbjtChgFgNm":"","abeekDgnPntCnt":null,"sbjtKorNm":"핵의학실습","sy41shtmRcomYn":"","genrl1stgNeceGrp":"","abeekGrpChoice":"","abeekSubmattFg":"","theoFgNm":"실습","abeekDetaSubmattFgNm":"","sy32shtmRcomYn":"","openTm":2.0,"pnt":2.0,"sbjtId":"14429","abeekChoiceSbjtCnt":null,"corsYy":"2019","subInspTotalPnt":null,"abeekGrpNm":"","rowStatus":1,"theoFg":"U0210002","curiNo":"2019106182"},{"submattFg":"U0209001","stgNeceGrpNm":"","sideTotalPnt":2.0,"sbjtChgFg":"","subDgnTotalPnt":null,"sy62shtmRcomYn":"○","abeekSubmattFgNm":"","sustLsnFgNm":"전필","sy12shtmRcomYn":"","sy42shtmRcomYn":"","abeekInspPracPntCnt":null,"genrl1stgNeceSbjtCnt":null,"abeekSustLsnFg":"","abeekDetaSubmattFg":"","sy51shtmRcomYn":"","abeekSustLsnFgNm":"","sy11shtmRcomYn":"","abeekTheoPntCnt":null,"sy31shtmRcomYn":"","submattFgNm":"전공과목","sbjtCd":"18338","subTheoTotalPnt":null,"mjCd":"DS03008002001","sy61shtmRcomYn":"○","sy22shtmRcomYn":"","mjCdNm":"의학전공(과)","sustLsnFg":"U0208004","sy52shtmRcomYn":"","sy21shtmRcomYn":"","sbjtChgFgNm":"","abeekDgnPntCnt":null,"sbjtKorNm":"영상의학실습","sy41shtmRcomYn":"","genrl1stgNeceGrp":"","abeekGrpChoice":"","abeekSubmattFg":"","theoFgNm":"실습","abeekDetaSubmattFgNm":"","sy32shtmRcomYn":"","openTm":null,"pnt":2.0,"sbjtId":"18338","abeekChoiceSbjtCnt":null,"corsYy":"2019","subInspTotalPnt":null,"abeekGrpNm":"","rowStatus":1,"theoFg":"U0210002","curiNo":"2019106183"},{"submattFg":"U0209001","stgNeceGrpNm":"","sideTotalPnt":3.0,"sbjtChgFg":"U0212002","subDgnTotalPnt":null,"sy62shtmRcomYn":"","abeekSubmattFgNm":"","sustLsnFgNm":"전필","sy12shtmRcomYn":"","sy42shtmRcomYn":"","abeekInspPracPntCnt":null,"genrl1stgNeceSbjtCnt":null,"abeekSustLsnFg":"","abeekDetaSubmattFg":"","sy51shtmRcomYn":"","abeekSustLsnFgNm":"","sy11shtmRcomYn":"","abeekTheoPntCnt":null,"sy31shtmRcomYn":"","submattFgNm":"전공과목","sbjtCd":"19119","subTheoTotalPnt":null,"mjCd":"DS03008002001","sy61shtmRcomYn":"","sy22shtmRcomYn":"○","mjCdNm":"의학전공(과)","sustLsnFg":"U0208004","sy52shtmRcomYn":"","sy21shtmRcomYn":"","sbjtChgFgNm":"변경","abeekDgnPntCnt":null,"sbjtKorNm":"분자생물학","sy41shtmRcomYn":"","genrl1stgNeceGrp":"","abeekGrpChoice":"","abeekSubmattFg":"","theoFgNm":"이론","abeekDetaSubmattFgNm":"","sy32shtmRcomYn":"","openTm":3.0,"pnt":3.0,"sbjtId":"19119","abeekChoiceSbjtCnt":null,"corsYy":"2019","subInspTotalPnt":null,"abeekGrpNm":"","rowStatus":1,"theoFg":"U0210001","curiNo":"2019106184"},{"submattFg":"U0209001","stgNeceGrpNm":"","sideTotalPnt":1.0,"sbjtChgFg":"","subDgnTotalPnt":null,"sy62shtmRcomYn":"","abeekSubmattFgNm":"","sustLsnFgNm":"전필","sy12shtmRcomYn":"","sy42shtmRcomYn":"","abeekInspPracPntCnt":null,"genrl1stgNeceSbjtCnt":null,"abeekSustLsnFg":"","abeekDetaSubmattFg":"","sy51shtmRcomYn":"○","abeekSustLsnFgNm":"","sy11shtmRcomYn":"","abeekTheoPntCnt":null,"sy31shtmRcomYn":"","submattFgNm":"전공과목","sbjtCd":"19417","subTheoTotalPnt":null,"mjCd":"DS03008002001","sy61shtmRcomYn":"","sy22shtmRcomYn":"","mjCdNm":"의학전공(과)","sustLsnFg":"U0208004","sy52shtmRcomYn":"○","sy21shtmRcomYn":"","sbjtChgFgNm":"","abeekDgnPntCnt":null,"sbjtKorNm":"보완통합의학","sy41shtmRcomYn":"","genrl1stgNeceGrp":"","abeekGrpChoice":"","abeekSubmattFg":"","theoFgNm":"이론","abeekDetaSubmattFgNm":"","sy32shtmRcomYn":"","openTm":6.0,"pnt":1.0,"sbjtId":"19417","abeekChoiceSbjtCnt":null,"corsYy":"2019","subInspTotalPnt":null,"abeekGrpNm":"","rowStatus":1,"theoFg":"U0210001","curiNo":"2019106185"},{"submattFg":"U0209001","stgNeceGrpNm":"","sideTotalPnt":4.0,"sbjtChgFg":"","subDgnTotalPnt":null,"sy62shtmRcomYn":"","abeekSubmattFgNm":"","sustLsnFgNm":"전필","sy12shtmRcomYn":"","sy42shtmRcomYn":"","abeekInspPracPntCnt":null,"genrl1stgNeceSbjtCnt":null,"abeekSustLsnFg":"","abeekDetaSubmattFg":"","sy51shtmRcomYn":"○","abeekSustLsnFgNm":"","sy11shtmRcomYn":"","abeekTheoPntCnt":null,"sy31shtmRcomYn":"","submattFgNm":"전공과목","sbjtCd":"19420","subTheoTotalPnt":null,"mjCd":"DS03008002001","sy61shtmRcomYn":"","sy22shtmRcomYn":"","mjCdNm":"의학전공(과)","sustLsnFg":"U0208004","sy52shtmRcomYn":"○","sy21shtmRcomYn":"","sbjtChgFgNm":"","abeekDgnPntCnt":null,"sbjtKorNm":"소아청소년과학실습","sy41shtmRcomYn":"","genrl1stgNeceGrp":"","abeekGrpChoice":"","abeekSubmattFg":"","theoFgNm":"실습","abeekDetaSubmattFgNm":"","sy32shtmRcomYn":"","openTm":null,"pnt":4.0,"sbjtId":"19420","abeekChoiceSbjtCnt":null,"corsYy":"2019","subInspTotalPnt":null,"abeekGrpNm":"","rowStatus":1,"theoFg":"U0210002","curiNo":"2019106186"},{"submattFg":"U0209001","stgNeceGrpNm":"","sideTotalPnt":2.0,"sbjtChgFg":"U0212002","subDgnTotalPnt":null,"sy62shtmRcomYn":"","abeekSubmattFgNm":"","sustLsnFgNm":"전필","sy12shtmRcomYn":"","sy42shtmRcomYn":"","abeekInspPracPntCnt":null,"genrl1stgNeceSbjtCnt":null,"abeekSustLsnFg":"","abeekDetaSubmattFg":"","sy51shtmRcomYn":"","abeekSustLsnFgNm":"","sy11shtmRcomYn":"","abeekTheoPntCnt":null,"sy31shtmRcomYn":"","submattFgNm":"전공과목","sbjtCd":"22403","subTheoTotalPnt":null,"mjCd":"DS03008002001","sy61shtmRcomYn":"","sy22shtmRcomYn":"","mjCdNm":"의학전공(과)","sustLsnFg":"U0208004","sy52shtmRcomYn":"","sy21shtmRcomYn":"","sbjtChgFgNm":"변경","abeekDgnPntCnt":null,"sbjtKorNm":"임상의학총론","sy41shtmRcomYn":"","genrl1stgNeceGrp":"","abeekGrpChoice":"","abeekSubmattFg":"","theoFgNm":"이론","abeekDetaSubmattFgNm":"","sy32shtmRcomYn":"○","openTm":1.0,"pnt":2.0,"sbjtId":"22403","abeekChoiceSbjtCnt":null,"corsYy":"2019","subInspTotalPnt":null,"abeekGrpNm":"","rowStatus":1,"theoFg":"U0210001","curiNo":"2019106187"},{"submattFg":"U0209001","stgNeceGrpNm":"","sideTotalPnt":6.0,"sbjtChgFg":"","subDgnTotalPnt":null,"sy62shtmRcomYn":"","abeekSubmattFgNm":"","sustLsnFgNm":"전필","sy12shtmRcomYn":"","sy42shtmRcomYn":"","abeekInspPracPntCnt":null,"genrl1stgNeceSbjtCnt":null,"abeekSustLsnFg":"","abeekDetaSubmattFg":"","sy51shtmRcomYn":"","abeekSustLsnFgNm":"","sy11shtmRcomYn":"","abeekTheoPntCnt":null,"sy31shtmRcomYn":"","submattFgNm":"전공과목","sbjtCd":"22404","subTheoTotalPnt":null,"mjCd":"DS03008002001","sy61shtmRcomYn":"","sy22shtmRcomYn":"","mjCdNm":"의학전공(과)","sustLsnFg":"U0208004","sy52shtmRcomYn":"","sy21shtmRcomYn":"","sbjtChgFgNm":"","abeekDgnPntCnt":null,"sbjtKorNm":"감염과 면역","sy41shtmRcomYn":"","genrl1stgNeceGrp":"","abeekGrpChoice":"","abeekSubmattFg":"","theoFgNm":"이론","abeekDetaSubmattFgNm":"","sy32shtmRcomYn":"","openTm":6.0,"pnt":6.0,"sbjtId":"22404","abeekChoiceSbjtCnt":null,"corsYy":"2019","subInspTotalPnt":null,"abeekGrpNm":"","rowStatus":1,"theoFg":"U0210001","curiNo":"2019106188"},{"submattFg":"U0209001","stgNeceGrpNm":"","sideTotalPnt":8.0,"sbjtChgFg":"","subDgnTotalPnt":null,"sy62shtmRcomYn":"","abeekSubmattFgNm":"","sustLsnFgNm":"전필","sy12shtmRcomYn":"","sy42shtmRcomYn":"","abeekInspPracPntCnt":null,"genrl1stgNeceSbjtCnt":null,"abeekSustLsnFg":"","abeekDetaSubmattFg":"","sy51shtmRcomYn":"","abeekSustLsnFgNm":"","sy11shtmRcomYn":"","abeekTheoPntCnt":null,"sy31shtmRcomYn":"","submattFgNm":"전공과목","sbjtCd":"22406","subTheoTotalPnt":null,"mjCd":"DS03008002001","sy61shtmRcomYn":"","sy22shtmRcomYn":"","mjCdNm":"의학전공(과)","sustLsnFg":"U0208004","sy52shtmRcomYn":"","sy21shtmRcomYn":"","sbjtChgFgNm":"","abeekDgnPntCnt":null,"sbjtKorNm":"소화기","sy41shtmRcomYn":"","genrl1stgNeceGrp":"","abeekGrpChoice":"","abeekSubmattFg":"","theoFgNm":"이론","abeekDetaSubmattFgNm":"","sy32shtmRcomYn":"○","openTm":8.0,"pnt":8.0,"sbjtId":"22406","abeekChoiceSbjtCnt":null,"corsYy":"2019","subInspTotalPnt":null,"abeekGrpNm":"","rowStatus":1,"theoFg":"U0210001","curiNo":"2019106189"},{"submattFg":"U0209001","stgNeceGrpNm":"","sideTotalPnt":6.0,"sbjtChgFg":"","subDgnTotalPnt":null,"sy62shtmRcomYn":"","abeekSubmattFgNm":"","sustLsnFgNm":"전필","sy12shtmRcomYn":"","sy42shtmRcomYn":"","abeekInspPracPntCnt":null,"genrl1stgNeceSbjtCnt":null,"abeekSustLsnFg":"","abeekDetaSubmattFg":"","sy51shtmRcomYn":"","abeekSustLsnFgNm":"","sy11shtmRcomYn":"","abeekTheoPntCnt":null,"sy31shtmRcomYn":"","submattFgNm":"전공과목","sbjtCd":"22407","subTheoTotalPnt":null,"mjCd":"DS03008002001","sy61shtmRcomYn":"","sy22shtmRcomYn":"","mjCdNm":"의학전공(과)","sustLsnFg":"U0208004","sy52shtmRcomYn":"","sy21shtmRcomYn":"","sbjtChgFgNm":"","abeekDgnPntCnt":null,"sbjtKorNm":"호흡기","sy41shtmRcomYn":"","genrl1stgNeceGrp":"","abeekGrpChoice":"","abeekSubmattFg":"","theoFgNm":"이론","abeekDetaSubmattFgNm":"","sy32shtmRcomYn":"○","openTm":6.0,"pnt":6.0,"sbjtId":"22407","abeekChoiceSbjtCnt":null,"corsYy":"2019","subInspTotalPnt":null,"abeekGrpNm":"","rowStatus":1,"theoFg":"U0210001","curiNo":"2019106190"},{"submattFg":"U0209001","stgNeceGrpNm":"","sideTotalPnt":1.0,"sbjtChgFg":"","subDgnTotalPnt":null,"sy62shtmRcomYn":"○","abeekSubmattFgNm":"","sustLsnFgNm":"전필","sy12shtmRcomYn":"","sy42shtmRcomYn":"","abeekInspPracPntCnt":null,"genrl1stgNeceSbjtCnt":null,"abeekSustLsnFg":"","abeekDetaSubmattFg":"","sy51shtmRcomYn":"","abeekSustLsnFgNm":"","sy11shtmRcomYn":"","abeekTheoPntCnt":null,"sy31shtmRcomYn":"","submattFgNm":"전공과목","sbjtCd":"8626","subTheoTotalPnt":null,"mjCd":"DS03008002001","sy61shtmRcomYn":"○","sy22shtmRcomYn":"","mjCdNm":"의학전공(과)","sustLsnFg":"U0208004","sy52shtmRcomYn":"","sy21shtmRcomYn":"","sbjtChgFgNm":"","abeekDgnPntCnt":null,"sbjtKorNm":"의료정보학","sy41shtmRcomYn":"","genrl1stgNeceGrp":"","abeekGrpChoice":"","abeekSubmattFg":"","theoFgNm":"이론+실습","abeekDetaSubmattFgNm":"","sy32shtmRcomYn":"","openTm":2.0,"pnt":1.0,"sbjtId":"8626","abeekChoiceSbjtCnt":null,"corsYy":"2019","subInspTotalPnt":null,"abeekGrpNm":"","rowStatus":1,"theoFg":"U0210005","curiNo":"2019106191"},{"submattFg":"U0209001","stgNeceGrpNm":"","sideTotalPnt":7.0,"sbjtChgFg":"","subDgnTotalPnt":null,"sy62shtmRcomYn":"","abeekSubmattFgNm":"","sustLsnFgNm":"전필","sy12shtmRcomYn":"","sy42shtmRcomYn":"","abeekInspPracPntCnt":null,"genrl1stgNeceSbjtCnt":null,"abeekSustLsnFg":"","abeekDetaSubmattFg":"","sy51shtmRcomYn":"○","abeekSustLsnFgNm":"","sy11shtmRcomYn":"","abeekTheoPntCnt":null,"sy31shtmRcomYn":"","submattFgNm":"전공과목","sbjtCd":"9155","subTheoTotalPnt":null,"mjCd":"DS03008002001","sy61shtmRcomYn":"","sy22shtmRcomYn":"","mjCdNm":"의학전공(과)","sustLsnFg":"U0208004","sy52shtmRcomYn":"○","sy21shtmRcomYn":"","sbjtChgFgNm":"","abeekDgnPntCnt":null,"sbjtKorNm":"내과학실습","sy41shtmRcomYn":"","genrl1stgNeceGrp":"","abeekGrpChoice":"","abeekSubmattFg":"","theoFgNm":"실습","abeekDetaSubmattFgNm":"","sy32shtmRcomYn":"","openTm":14.0,"pnt":7.0,"sbjtId":"9155","abeekChoiceSbjtCnt":null,"corsYy":"2019","subInspTotalPnt":null,"abeekGrpNm":"","rowStatus":1,"theoFg":"U0210002","curiNo":"2019106192"},{"submattFg":"U0209001","stgNeceGrpNm":"","sideTotalPnt":2.0,"sbjtChgFg":"","subDgnTotalPnt":null,"sy62shtmRcomYn":"○","abeekSubmattFgNm":"","sustLsnFgNm":"전필","sy12shtmRcomYn":"","sy42shtmRcomYn":"","abeekInspPracPntCnt":null,"genrl1stgNeceSbjtCnt":null,"abeekSustLsnFg":"","abeekDetaSubmattFg":"","sy51shtmRcomYn":"","abeekSustLsnFgNm":"","sy11shtmRcomYn":"","abeekTheoPntCnt":null,"sy31shtmRcomYn":"","submattFgNm":"전공과목","sbjtCd":"9744","subTheoTotalPnt":null,"mjCd":"DS03008002001","sy61shtmRcomYn":"○","sy22shtmRcomYn":"","mjCdNm":"의학전공(과)","sustLsnFg":"U0208004","sy52shtmRcomYn":"","sy21shtmRcomYn":"","sbjtChgFgNm":"","abeekDgnPntCnt":null,"sbjtKorNm":"가정의학과학실습","sy41shtmRcomYn":"","genrl1stgNeceGrp":"","abeekGrpChoice":"","abeekSubmattFg":"","theoFgNm":"실습","abeekDetaSubmattFgNm":"","sy32shtmRcomYn":"","openTm":2.0,"pnt":2.0,"sbjtId":"9744","abeekChoiceSbjtCnt":null,"corsYy":"2019","subInspTotalPnt":null,"abeekGrpNm":"","rowStatus":1,"theoFg":"U0210002","curiNo":"2019106193"},{"submattFg":"U0209001","stgNeceGrpNm":"","sideTotalPnt":2.0,"sbjtChgFg":"U0212002","subDgnTotalPnt":null,"sy62shtmRcomYn":"","abeekSubmattFgNm":"","sustLsnFgNm":"전필","sy12shtmRcomYn":"","sy42shtmRcomYn":"","abeekInspPracPntCnt":null,"genrl1stgNeceSbjtCnt":null,"abeekSustLsnFg":"","abeekDetaSubmattFg":"","sy51shtmRcomYn":"","abeekSustLsnFgNm":"","sy11shtmRcomYn":"","abeekTheoPntCnt":null,"sy31shtmRcomYn":"","submattFgNm":"전공과목","sbjtCd":"BIO231","subTheoTotalPnt":null,"mjCd":"DS03008002001","sy61shtmRcomYn":"","sy22shtmRcomYn":"○","mjCdNm":"의학전공(과)","sustLsnFg":"U0208004","sy52shtmRcomYn":"","sy21shtmRcomYn":"","sbjtChgFgNm":"변경","abeekDgnPntCnt":null,"sbjtKorNm":"세포생물학","sy41shtmRcomYn":"","genrl1stgNeceGrp":"","abeekGrpChoice":"","abeekSubmattFg":"","theoFgNm":"이론","abeekDetaSubmattFgNm":"","sy32shtmRcomYn":"","openTm":2.0,"pnt":2.0,"sbjtId":"1045","abeekChoiceSbjtCnt":null,"corsYy":"2019","subInspTotalPnt":null,"abeekGrpNm":"","rowStatus":1,"theoFg":"U0210001","curiNo":"2019106194"},{"submattFg":"U0209001","stgNeceGrpNm":"","sideTotalPnt":3.0,"sbjtChgFg":"","subDgnTotalPnt":null,"sy62shtmRcomYn":"","abeekSubmattFgNm":"","sustLsnFgNm":"전필","sy12shtmRcomYn":"","sy42shtmRcomYn":"","abeekInspPracPntCnt":null,"genrl1stgNeceSbjtCnt":null,"abeekSustLsnFg":"","abeekDetaSubmattFg":"","sy51shtmRcomYn":"","abeekSustLsnFgNm":"","sy11shtmRcomYn":"","abeekTheoPntCnt":null,"sy31shtmRcomYn":"","submattFgNm":"전공과목","sbjtCd":"CCMP203","subTheoTotalPnt":null,"mjCd":"DS03008002001","sy61shtmRcomYn":"","sy22shtmRcomYn":"","mjCdNm":"의학전공(과)","sustLsnFg":"U0208004","sy52shtmRcomYn":"","sy21shtmRcomYn":"○","sbjtChgFgNm":"","abeekDgnPntCnt":null,"sbjtKorNm":"컴퓨터활용을 통한 의과학자료 처리 및 분석","sy41shtmRcomYn":"","genrl1stgNeceGrp":"","abeekGrpChoice":"","abeekSubmattFg":"","theoFgNm":"이론+실습","abeekDetaSubmattFgNm":"","sy32shtmRcomYn":"","openTm":3.0,"pnt":3.0,"sbjtId":"20110202","abeekChoiceSbjtCnt":null,"corsYy":"2019","subInspTotalPnt":null,"abeekGrpNm":"","rowStatus":1,"theoFg":"U0210005","curiNo":"2019106195"},{"submattFg":"U0209001","stgNeceGrpNm":"","sideTotalPnt":2.0,"sbjtChgFg":"","subDgnTotalPnt":null,"sy62shtmRcomYn":"","abeekSubmattFgNm":"","sustLsnFgNm":"전필","sy12shtmRcomYn":"","sy42shtmRcomYn":"","abeekInspPracPntCnt":null,"genrl1stgNeceSbjtCnt":null,"abeekSustLsnFg":"","abeekDetaSubmattFg":"","sy51shtmRcomYn":"","abeekSustLsnFgNm":"","sy11shtmRcomYn":"○","abeekTheoPntCnt":null,"sy31shtmRcomYn":"","submattFgNm":"전공과목","sbjtCd":"MED104","subTheoTotalPnt":null,"mjCd":"DS03008002001","sy61shtmRcomYn":"","sy22shtmRcomYn":"","mjCdNm":"의학전공(과)","sustLsnFg":"U0208004","sy52shtmRcomYn":"","sy21shtmRcomYn":"","sbjtChgFgNm":"","abeekDgnPntCnt":null,"sbjtKorNm":"의료인문학1","sy41shtmRcomYn":"","genrl1stgNeceGrp":"","abeekGrpChoice":"","abeekSubmattFg":"","theoFgNm":"이론+실습","abeekDetaSubmattFgNm":"","sy32shtmRcomYn":"","openTm":2.0,"pnt":2.0,"sbjtId":"20170567","abeekChoiceSbjtCnt":null,"corsYy":"2019","subInspTotalPnt":null,"abeekGrpNm":"","rowStatus":1,"theoFg":"U0210005","curiNo":"2019106196"},{"submattFg":"U0209001","stgNeceGrpNm":"","sideTotalPnt":2.0,"sbjtChgFg":"","subDgnTotalPnt":null,"sy62shtmRcomYn":"","abeekSubmattFgNm":"","sustLsnFgNm":"전필","sy12shtmRcomYn":"","sy42shtmRcomYn":"","abeekInspPracPntCnt":null,"genrl1stgNeceSbjtCnt":null,"abeekSustLsnFg":"","abeekDetaSubmattFg":"","sy51shtmRcomYn":"","abeekSustLsnFgNm":"","sy11shtmRcomYn":"","abeekTheoPntCnt":null,"sy31shtmRcomYn":"","submattFgNm":"전공과목","sbjtCd":"MED203","subTheoTotalPnt":null,"mjCd":"DS03008002001","sy61shtmRcomYn":"","sy22shtmRcomYn":"○","mjCdNm":"의학전공(과)","sustLsnFg":"U0208004","sy52shtmRcomYn":"","sy21shtmRcomYn":"","sbjtChgFgNm":"","abeekDgnPntCnt":null,"sbjtKorNm":"실용의학영어","sy41shtmRcomYn":"","genrl1stgNeceGrp":"","abeekGrpChoice":"","abeekSubmattFg":"","theoFgNm":"이론","abeekDetaSubmattFgNm":"","sy32shtmRcomYn":"","openTm":2.0,"pnt":2.0,"sbjtId":"20100379","abeekChoiceSbjtCnt":null,"corsYy":"2019","subInspTotalPnt":null,"abeekGrpNm":"","rowStatus":1,"theoFg":"U0210001","curiNo":"2019106198"},{"submattFg":"U0209001","stgNeceGrpNm":"","sideTotalPnt":2.0,"sbjtChgFg":"","subDgnTotalPnt":null,"sy62shtmRcomYn":"","abeekSubmattFgNm":"","sustLsnFgNm":"전필","sy12shtmRcomYn":"","sy42shtmRcomYn":"","abeekInspPracPntCnt":null,"genrl1stgNeceSbjtCnt":null,"abeekSustLsnFg":"","abeekDetaSubmattFg":"","sy51shtmRcomYn":"","abeekSustLsnFgNm":"","sy11shtmRcomYn":"","abeekTheoPntCnt":null,"sy31shtmRcomYn":"","submattFgNm":"전공과목","sbjtCd":"MED204","subTheoTotalPnt":null,"mjCd":"DS03008002001","sy61shtmRcomYn":"","sy22shtmRcomYn":"","mjCdNm":"의학전공(과)","sustLsnFg":"U0208004","sy52shtmRcomYn":"","sy21shtmRcomYn":"○","sbjtChgFgNm":"","abeekDgnPntCnt":null,"sbjtKorNm":"의학용어","sy41shtmRcomYn":"","genrl1stgNeceGrp":"","abeekGrpChoice":"","abeekSubmattFg":"","theoFgNm":"이론","abeekDetaSubmattFgNm":"","sy32shtmRcomYn":"","openTm":2.0,"pnt":2.0,"sbjtId":"20100380","abeekChoiceSbjtCnt":null,"corsYy":"2019","subInspTotalPnt":null,"abeekGrpNm":"","rowStatus":1,"theoFg":"U0210001","curiNo":"2019106199"},{"submattFg":"U0209001","stgNeceGrpNm":"","sideTotalPnt":2.0,"sbjtChgFg":"","subDgnTotalPnt":null,"sy62shtmRcomYn":"","abeekSubmattFgNm":"","sustLsnFgNm":"전필","sy12shtmRcomYn":"○","sy42shtmRcomYn":"","abeekInspPracPntCnt":null,"genrl1stgNeceSbjtCnt":null,"abeekSustLsnFg":"","abeekDetaSubmattFg":"","sy51shtmRcomYn":"","abeekSustLsnFgNm":"","sy11shtmRcomYn":"","abeekTheoPntCnt":null,"sy31shtmRcomYn":"","submattFgNm":"전공과목","sbjtCd":"MED205","subTheoTotalPnt":null,"mjCd":"DS03008002001","sy61shtmRcomYn":"","sy22shtmRcomYn":"","mjCdNm":"의학전공(과)","sustLsnFg":"U0208004","sy52shtmRcomYn":"","sy21shtmRcomYn":"","sbjtChgFgNm":"","abeekDgnPntCnt":null,"sbjtKorNm":"의과학기초연구 1","sy41shtmRcomYn":"","genrl1stgNeceGrp":"","abeekGrpChoice":"","abeekSubmattFg":"","theoFgNm":"이론+실습","abeekDetaSubmattFgNm":"","sy32shtmRcomYn":"","openTm":2.0,"pnt":2.0,"sbjtId":"20120861","abeekChoiceSbjtCnt":null,"corsYy":"2019","subInspTotalPnt":null,"abeekGrpNm":"","rowStatus":1,"theoFg":"U0210005","curiNo":"2019106161"},{"submattFg":"U0209001","stgNeceGrpNm":"","sideTotalPnt":2.0,"sbjtChgFg":"","subDgnTotalPnt":null,"sy62shtmRcomYn":"","abeekSubmattFgNm":"","sustLsnFgNm":"전필","sy12shtmRcomYn":"","sy42shtmRcomYn":"","abeekInspPracPntCnt":null,"genrl1stgNeceSbjtCnt":null,"abeekSustLsnFg":"","abeekDetaSubmattFg":"","sy51shtmRcomYn":"","abeekSustLsnFgNm":"","sy11shtmRcomYn":"","abeekTheoPntCnt":null,"sy31shtmRcomYn":"","submattFgNm":"전공과목","sbjtCd":"MED207","subTheoTotalPnt":null,"mjCd":"DS03008002001","sy61shtmRcomYn":"","sy22shtmRcomYn":"○","mjCdNm":"의학전공(과)","sustLsnFg":"U0208004","sy52shtmRcomYn":"","sy21shtmRcomYn":"","sbjtChgFgNm":"","abeekDgnPntCnt":null,"sbjtKorNm":"의료인문학2","sy41shtmRcomYn":"","genrl1stgNeceGrp":"","abeekGrpChoice":"","abeekSubmattFg":"","theoFgNm":"이론+실습","abeekDetaSubmattFgNm":"","sy32shtmRcomYn":"","openTm":2.0,"pnt":2.0,"sbjtId":"20170565","abeekChoiceSbjtCnt":null,"corsYy":"2019","subInspTotalPnt":null,"abeekGrpNm":"","rowStatus":1,"theoFg":"U0210005","curiNo":"2019106200"},{"submattFg":"U0209001","stgNeceGrpNm":"","sideTotalPnt":3.0,"sbjtChgFg":"U0212002","subDgnTotalPnt":null,"sy62shtmRcomYn":"","abeekSubmattFgNm":"","sustLsnFgNm":"전필","sy12shtmRcomYn":"","sy42shtmRcomYn":"","abeekInspPracPntCnt":null,"genrl1stgNeceSbjtCnt":null,"abeekSustLsnFg":"","abeekDetaSubmattFg":"","sy51shtmRcomYn":"","abeekSustLsnFgNm":"","sy11shtmRcomYn":"","abeekTheoPntCnt":null,"sy31shtmRcomYn":"","submattFgNm":"전공과목","sbjtCd":"MED208","subTheoTotalPnt":null,"mjCd":"DS03008002001","sy61shtmRcomYn":"","sy22shtmRcomYn":"○","mjCdNm":"의학전공(과)","sustLsnFg":"U0208004","sy52shtmRcomYn":"","sy21shtmRcomYn":"","sbjtChgFgNm":"변경","abeekDgnPntCnt":null,"sbjtKorNm":"의학유전학","sy41shtmRcomYn":"","genrl1stgNeceGrp":"","abeekGrpChoice":"","abeekSubmattFg":"","theoFgNm":"이론","abeekDetaSubmattFgNm":"","sy32shtmRcomYn":"","openTm":3.0,"pnt":3.0,"sbjtId":"21431","abeekChoiceSbjtCnt":null,"corsYy":"2019","subInspTotalPnt":null,"abeekGrpNm":"","rowStatus":1,"theoFg":"U0210001","curiNo":"2019106197"},{"submattFg":"U0209001","stgNeceGrpNm":"","sideTotalPnt":1.0,"sbjtChgFg":"","subDgnTotalPnt":null,"sy62shtmRcomYn":"","abeekSubmattFgNm":"","sustLsnFgNm":"전필","sy12shtmRcomYn":"","sy42shtmRcomYn":"","abeekInspPracPntCnt":null,"genrl1stgNeceSbjtCnt":null,"abeekSustLsnFg":"","abeekDetaSubmattFg":"","sy51shtmRcomYn":"","abeekSustLsnFgNm":"","sy11shtmRcomYn":"","abeekTheoPntCnt":null,"sy31shtmRcomYn":"○","submattFgNm":"전공과목","sbjtCd":"MED301","subTheoTotalPnt":null,"mjCd":"DS03008002001","sy61shtmRcomYn":"","sy22shtmRcomYn":"","mjCdNm":"의학전공(과)","sustLsnFg":"U0208004","sy52shtmRcomYn":"","sy21shtmRcomYn":"","sbjtChgFgNm":"","abeekDgnPntCnt":null,"sbjtKorNm":"멘토와의 대화 1","sy41shtmRcomYn":"","genrl1stgNeceGrp":"","abeekGrpChoice":"","abeekSubmattFg":"","theoFgNm":"이론","abeekDetaSubmattFgNm":"","sy32shtmRcomYn":"○","openTm":1.0,"pnt":1.0,"sbjtId":"40041","abeekChoiceSbjtCnt":null,"corsYy":"2019","subInspTotalPnt":null,"abeekGrpNm":"","rowStatus":1,"theoFg":"U0210001","curiNo":"2019106201"},{"submattFg":"U0209001","stgNeceGrpNm":"","sideTotalPnt":6.0,"sbjtChgFg":"U0212002","subDgnTotalPnt":null,"sy62shtmRcomYn":"","abeekSubmattFgNm":"","sustLsnFgNm":"전필","sy12shtmRcomYn":"","sy42shtmRcomYn":"","abeekInspPracPntCnt":null,"genrl1stgNeceSbjtCnt":null,"abeekSustLsnFg":"","abeekDetaSubmattFg":"","sy51shtmRcomYn":"","abeekSustLsnFgNm":"","sy11shtmRcomYn":"","abeekTheoPntCnt":null,"sy31shtmRcomYn":"○","submattFgNm":"전공과목","sbjtCd":"MED3010","subTheoTotalPnt":null,"mjCd":"DS03008002001","sy61shtmRcomYn":"","sy22shtmRcomYn":"","mjCdNm":"의학전공(과)","sustLsnFg":"U0208004","sy52shtmRcomYn":"","sy21shtmRcomYn":"","sbjtChgFgNm":"변경","abeekDgnPntCnt":null,"sbjtKorNm":"면역과 감염체총론","sy41shtmRcomYn":"","genrl1stgNeceGrp":"","abeekGrpChoice":"","abeekSubmattFg":"","theoFgNm":"이론+실습","abeekDetaSubmattFgNm":"","sy32shtmRcomYn":"","openTm":4.0,"pnt":6.0,"sbjtId":"20110718","abeekChoiceSbjtCnt":null,"corsYy":"2019","subInspTotalPnt":null,"abeekGrpNm":"","rowStatus":1,"theoFg":"U0210005","curiNo":"2019106202"},{"submattFg":"U0209001","stgNeceGrpNm":"","sideTotalPnt":4.0,"sbjtChgFg":"","subDgnTotalPnt":null,"sy62shtmRcomYn":"","abeekSubmattFgNm":"","sustLsnFgNm":"전필","sy12shtmRcomYn":"","sy42shtmRcomYn":"","abeekInspPracPntCnt":null,"genrl1stgNeceSbjtCnt":null,"abeekSustLsnFg":"","abeekDetaSubmattFg":"","sy51shtmRcomYn":"","abeekSustLsnFgNm":"","sy11shtmRcomYn":"","abeekTheoPntCnt":null,"sy31shtmRcomYn":"○","submattFgNm":"전공과목","sbjtCd":"MED3012","subTheoTotalPnt":null,"mjCd":"DS03008002001","sy61shtmRcomYn":"","sy22shtmRcomYn":"","mjCdNm":"의학전공(과)","sustLsnFg":"U0208004","sy52shtmRcomYn":"","sy21shtmRcomYn":"","sbjtChgFgNm":"","abeekDgnPntCnt":null,"sbjtKorNm":"몸의구조 2","sy41shtmRcomYn":"","genrl1stgNeceGrp":"","abeekGrpChoice":"","abeekSubmattFg":"","theoFgNm":"이론","abeekDetaSubmattFgNm":"","sy32shtmRcomYn":"","openTm":3.0,"pnt":4.0,"sbjtId":"20120859","abeekChoiceSbjtCnt":null,"corsYy":"2019","subInspTotalPnt":null,"abeekGrpNm":"","rowStatus":1,"theoFg":"U0210001","curiNo":"2019106203"},{"submattFg":"U0209001","stgNeceGrpNm":"","sideTotalPnt":6.0,"sbjtChgFg":"U0212002","subDgnTotalPnt":null,"sy62shtmRcomYn":"","abeekSubmattFgNm":"","sustLsnFgNm":"전필","sy12shtmRcomYn":"","sy42shtmRcomYn":"","abeekInspPracPntCnt":null,"genrl1stgNeceSbjtCnt":null,"abeekSustLsnFg":"","abeekDetaSubmattFg":"","sy51shtmRcomYn":"","abeekSustLsnFgNm":"","sy11shtmRcomYn":"","abeekTheoPntCnt":null,"sy31shtmRcomYn":"○","submattFgNm":"전공과목","sbjtCd":"MED303","subTheoTotalPnt":null,"mjCd":"DS03008002001","sy61shtmRcomYn":"","sy22shtmRcomYn":"","mjCdNm":"의학전공(과)","sustLsnFg":"U0208004","sy52shtmRcomYn":"","sy21shtmRcomYn":"","sbjtChgFgNm":"변경","abeekDgnPntCnt":null,"sbjtKorNm":"몸의 기능과 조절","sy41shtmRcomYn":"","genrl1stgNeceGrp":"","abeekGrpChoice":"","abeekSubmattFg":"","theoFgNm":"이론","abeekDetaSubmattFgNm":"","sy32shtmRcomYn":"","openTm":4.0,"pnt":6.0,"sbjtId":"20110506","abeekChoiceSbjtCnt":null,"corsYy":"2019","subInspTotalPnt":null,"abeekGrpNm":"","rowStatus":1,"theoFg":"U0210001","curiNo":"2019106205"},{"submattFg":"U0209001","stgNeceGrpNm":"","sideTotalPnt":3.0,"sbjtChgFg":"","subDgnTotalPnt":null,"sy62shtmRcomYn":"","abeekSubmattFgNm":"","sustLsnFgNm":"전필","sy12shtmRcomYn":"","sy42shtmRcomYn":"","abeekInspPracPntCnt":null,"genrl1stgNeceSbjtCnt":null,"abeekSustLsnFg":"","abeekDetaSubmattFg":"","sy51shtmRcomYn":"","abeekSustLsnFgNm":"","sy11shtmRcomYn":"","abeekTheoPntCnt":null,"sy31shtmRcomYn":"","submattFgNm":"전공과목","sbjtCd":"MED305","subTheoTotalPnt":null,"mjCd":"DS03008002001","sy61shtmRcomYn":"","sy22shtmRcomYn":"","mjCdNm":"의학전공(과)","sustLsnFg":"U0208004","sy52shtmRcomYn":"","sy21shtmRcomYn":"","sbjtChgFgNm":"","abeekDgnPntCnt":null,"sbjtKorNm":"질병의 기초","sy41shtmRcomYn":"","genrl1stgNeceGrp":"","abeekGrpChoice":"","abeekSubmattFg":"","theoFgNm":"이론","abeekDetaSubmattFgNm":"","sy32shtmRcomYn":"○","openTm":null,"pnt":3.0,"sbjtId":"20110508","abeekChoiceSbjtCnt":null,"corsYy":"2019","subInspTotalPnt":null,"abeekGrpNm":"","rowStatus":1,"theoFg":"U0210001","curiNo":"2019106206"},{"submattFg":"U0209001","stgNeceGrpNm":"","sideTotalPnt":3.0,"sbjtChgFg":"U0212002","subDgnTotalPnt":null,"sy62shtmRcomYn":"","abeekSubmattFgNm":"","sustLsnFgNm":"전필","sy12shtmRcomYn":"","sy42shtmRcomYn":"","abeekInspPracPntCnt":null,"genrl1stgNeceSbjtCnt":null,"abeekSustLsnFg":"","abeekDetaSubmattFg":"","sy51shtmRcomYn":"","abeekSustLsnFgNm":"","sy11shtmRcomYn":"","abeekTheoPntCnt":null,"sy31shtmRcomYn":"","submattFgNm":"전공과목","sbjtCd":"MED306","subTheoTotalPnt":null,"mjCd":"DS03008002001","sy61shtmRcomYn":"","sy22shtmRcomYn":"","mjCdNm":"의학전공(과)","sustLsnFg":"U0208004","sy52shtmRcomYn":"","sy21shtmRcomYn":"","sbjtChgFgNm":"변경","abeekDgnPntCnt":null,"sbjtKorNm":"약물치료의 기초","sy41shtmRcomYn":"","genrl1stgNeceGrp":"","abeekGrpChoice":"","abeekSubmattFg":"","theoFgNm":"이론","abeekDetaSubmattFgNm":"","sy32shtmRcomYn":"○","openTm":null,"pnt":3.0,"sbjtId":"20110509","abeekChoiceSbjtCnt":null,"corsYy":"2019","subInspTotalPnt":null,"abeekGrpNm":"","rowStatus":1,"theoFg":"U0210001","curiNo":"2019106207"},{"submattFg":"U0209001","stgNeceGrpNm":"","sideTotalPnt":4.0,"sbjtChgFg":"U0212002","subDgnTotalPnt":null,"sy62shtmRcomYn":"","abeekSubmattFgNm":"","sustLsnFgNm":"전필","sy12shtmRcomYn":"","sy42shtmRcomYn":"","abeekInspPracPntCnt":null,"genrl1stgNeceSbjtCnt":null,"abeekSustLsnFg":"","abeekDetaSubmattFg":"","sy51shtmRcomYn":"","abeekSustLsnFgNm":"","sy11shtmRcomYn":"","abeekTheoPntCnt":null,"sy31shtmRcomYn":"○","submattFgNm":"전공과목","sbjtCd":"MED307","subTheoTotalPnt":null,"mjCd":"DS03008002001","sy61shtmRcomYn":"","sy22shtmRcomYn":"","mjCdNm":"의학전공(과)","sustLsnFg":"U0208004","sy52shtmRcomYn":"","sy21shtmRcomYn":"","sbjtChgFgNm":"변경","abeekDgnPntCnt":null,"sbjtKorNm":"몸의 구성성분","sy41shtmRcomYn":"","genrl1stgNeceGrp":"","abeekGrpChoice":"","abeekSubmattFg":"","theoFgNm":"이론+실습","abeekDetaSubmattFgNm":"","sy32shtmRcomYn":"","openTm":3.0,"pnt":4.0,"sbjtId":"20110511","abeekChoiceSbjtCnt":null,"corsYy":"2019","subInspTotalPnt":null,"abeekGrpNm":"","rowStatus":1,"theoFg":"U0210005","curiNo":"2019106208"},{"submattFg":"U0209001","stgNeceGrpNm":"","sideTotalPnt":2.0,"sbjtChgFg":"","subDgnTotalPnt":null,"sy62shtmRcomYn":"","abeekSubmattFgNm":"","sustLsnFgNm":"전필","sy12shtmRcomYn":"","sy42shtmRcomYn":"","abeekInspPracPntCnt":null,"genrl1stgNeceSbjtCnt":null,"abeekSustLsnFg":"","abeekDetaSubmattFg":"","sy51shtmRcomYn":"","abeekSustLsnFgNm":"","sy11shtmRcomYn":"","abeekTheoPntCnt":null,"sy31shtmRcomYn":"○","submattFgNm":"전공과목","sbjtCd":"MED308","subTheoTotalPnt":null,"mjCd":"DS03008002001","sy61shtmRcomYn":"","sy22shtmRcomYn":"","mjCdNm":"의학전공(과)","sustLsnFg":"U0208004","sy52shtmRcomYn":"","sy21shtmRcomYn":"","sbjtChgFgNm":"","abeekDgnPntCnt":null,"sbjtKorNm":"환자/의사/사회 1","sy41shtmRcomYn":"","genrl1stgNeceGrp":"","abeekGrpChoice":"","abeekSubmattFg":"","theoFgNm":"이론","abeekDetaSubmattFgNm":"","sy32shtmRcomYn":"","openTm":null,"pnt":2.0,"sbjtId":"20110645","abeekChoiceSbjtCnt":null,"corsYy":"2019","subInspTotalPnt":null,"abeekGrpNm":"","rowStatus":1,"theoFg":"U0210001","curiNo":"2019106209"},{"submattFg":"U0209001","stgNeceGrpNm":"","sideTotalPnt":2.0,"sbjtChgFg":"","subDgnTotalPnt":null,"sy62shtmRcomYn":"","abeekSubmattFgNm":"","sustLsnFgNm":"전필","sy12shtmRcomYn":"","sy42shtmRcomYn":"","abeekInspPracPntCnt":null,"genrl1stgNeceSbjtCnt":null,"abeekSustLsnFg":"","abeekDetaSubmattFg":"","sy51shtmRcomYn":"","abeekSustLsnFgNm":"","sy11shtmRcomYn":"","abeekTheoPntCnt":null,"sy31shtmRcomYn":"","submattFgNm":"전공과목","sbjtCd":"MED309","subTheoTotalPnt":null,"mjCd":"DS03008002001","sy61shtmRcomYn":"","sy22shtmRcomYn":"","mjCdNm":"의학전공(과)","sustLsnFg":"U0208004","sy52shtmRcomYn":"","sy21shtmRcomYn":"","sbjtChgFgNm":"","abeekDgnPntCnt":null,"sbjtKorNm":"임상실습입문 1","sy41shtmRcomYn":"","genrl1stgNeceGrp":"","abeekGrpChoice":"","abeekSubmattFg":"","theoFgNm":"실습","abeekDetaSubmattFgNm":"","sy32shtmRcomYn":"○","openTm":2.0,"pnt":2.0,"sbjtId":"20110648","abeekChoiceSbjtCnt":null,"corsYy":"2019","subInspTotalPnt":null,"abeekGrpNm":"","rowStatus":1,"theoFg":"U0210002","curiNo":"2019106210"},{"submattFg":"U0209001","stgNeceGrpNm":"","sideTotalPnt":6.0,"sbjtChgFg":"","subDgnTotalPnt":null,"sy62shtmRcomYn":"","abeekSubmattFgNm":"","sustLsnFgNm":"전필","sy12shtmRcomYn":"","sy42shtmRcomYn":"","abeekInspPracPntCnt":null,"genrl1stgNeceSbjtCnt":null,"abeekSustLsnFg":"","abeekDetaSubmattFg":"","sy51shtmRcomYn":"","abeekSustLsnFgNm":"","sy11shtmRcomYn":"","abeekTheoPntCnt":null,"sy31shtmRcomYn":"","submattFgNm":"전공과목","sbjtCd":"MED401","subTheoTotalPnt":null,"mjCd":"DS03008002001","sy61shtmRcomYn":"","sy22shtmRcomYn":"","mjCdNm":"의학전공(과)","sustLsnFg":"U0208004","sy52shtmRcomYn":"","sy21shtmRcomYn":"","sbjtChgFgNm":"","abeekDgnPntCnt":null,"sbjtKorNm":"순환기","sy41shtmRcomYn":"○","genrl1stgNeceGrp":"","abeekGrpChoice":"","abeekSubmattFg":"","theoFgNm":"이론+실습","abeekDetaSubmattFgNm":"","sy32shtmRcomYn":"","openTm":6.0,"pnt":6.0,"sbjtId":"40010","abeekChoiceSbjtCnt":null,"corsYy":"2019","subInspTotalPnt":null,"abeekGrpNm":"","rowStatus":1,"theoFg":"U0210005","curiNo":"2019106211"},{"submattFg":"U0209001","stgNeceGrpNm":"","sideTotalPnt":5.0,"sbjtChgFg":"","subDgnTotalPnt":null,"sy62shtmRcomYn":"","abeekSubmattFgNm":"","sustLsnFgNm":"전필","sy12shtmRcomYn":"","sy42shtmRcomYn":"○","abeekInspPracPntCnt":null,"genrl1stgNeceSbjtCnt":null,"abeekSustLsnFg":"","abeekDetaSubmattFg":"","sy51shtmRcomYn":"","abeekSustLsnFgNm":"","sy11shtmRcomYn":"","abeekTheoPntCnt":null,"sy31shtmRcomYn":"","submattFgNm":"전공과목","sbjtCd":"MED4010","subTheoTotalPnt":null,"mjCd":"DS03008002001","sy61shtmRcomYn":"","sy22shtmRcomYn":"","mjCdNm":"의학전공(과)","sustLsnFg":"U0208004","sy52shtmRcomYn":"","sy21shtmRcomYn":"","sbjtChgFgNm":"","abeekDgnPntCnt":null,"sbjtKorNm":"정신과 행동","sy41shtmRcomYn":"","genrl1stgNeceGrp":"","abeekGrpChoice":"","abeekSubmattFg":"","theoFgNm":"이론","abeekDetaSubmattFgNm":"","sy32shtmRcomYn":"","openTm":5.0,"pnt":5.0,"sbjtId":"40019","abeekChoiceSbjtCnt":null,"corsYy":"2019","subInspTotalPnt":null,"abeekGrpNm":"","rowStatus":1,"theoFg":"U0210001","curiNo":"2019106212"},{"submattFg":"U0209001","stgNeceGrpNm":"","sideTotalPnt":6.0,"sbjtChgFg":"","subDgnTotalPnt":null,"sy62shtmRcomYn":"","abeekSubmattFgNm":"","sustLsnFgNm":"전필","sy12shtmRcomYn":"","sy42shtmRcomYn":"○","abeekInspPracPntCnt":null,"genrl1stgNeceSbjtCnt":null,"abeekSustLsnFg":"","abeekDetaSubmattFg":"","sy51shtmRcomYn":"","abeekSustLsnFgNm":"","sy11shtmRcomYn":"","abeekTheoPntCnt":null,"sy31shtmRcomYn":"","submattFgNm":"전공과목","sbjtCd":"MED4011","subTheoTotalPnt":null,"mjCd":"DS03008002001","sy61shtmRcomYn":"","sy22shtmRcomYn":"","mjCdNm":"의학전공(과)","sustLsnFg":"U0208004","sy52shtmRcomYn":"","sy21shtmRcomYn":"","sbjtChgFgNm":"","abeekDgnPntCnt":null,"sbjtKorNm":"건강증진과 예방","sy41shtmRcomYn":"","genrl1stgNeceGrp":"","abeekGrpChoice":"","abeekSubmattFg":"","theoFgNm":"이론+실습","abeekDetaSubmattFgNm":"","sy32shtmRcomYn":"","openTm":6.0,"pnt":6.0,"sbjtId":"40020","abeekChoiceSbjtCnt":null,"corsYy":"2019","subInspTotalPnt":null,"abeekGrpNm":"","rowStatus":1,"theoFg":"U0210005","curiNo":"2019106213"},{"submattFg":"U0209001","stgNeceGrpNm":"","sideTotalPnt":1.0,"sbjtChgFg":"","subDgnTotalPnt":null,"sy62shtmRcomYn":"","abeekSubmattFgNm":"","sustLsnFgNm":"전필","sy12shtmRcomYn":"","sy42shtmRcomYn":"○","abeekInspPracPntCnt":null,"genrl1stgNeceSbjtCnt":null,"abeekSustLsnFg":"","abeekDetaSubmattFg":"","sy51shtmRcomYn":"","abeekSustLsnFgNm":"","sy11shtmRcomYn":"","abeekTheoPntCnt":null,"sy31shtmRcomYn":"","submattFgNm":"전공과목","sbjtCd":"MED4013","subTheoTotalPnt":null,"mjCd":"DS03008002001","sy61shtmRcomYn":"","sy22shtmRcomYn":"","mjCdNm":"의학전공(과)","sustLsnFg":"U0208004","sy52shtmRcomYn":"","sy21shtmRcomYn":"","sbjtChgFgNm":"","abeekDgnPntCnt":null,"sbjtKorNm":"멘토와의 대화 2","sy41shtmRcomYn":"○","genrl1stgNeceGrp":"","abeekGrpChoice":"","abeekSubmattFg":"","theoFgNm":"이론","abeekDetaSubmattFgNm":"","sy32shtmRcomYn":"","openTm":1.0,"pnt":1.0,"sbjtId":"40042","abeekChoiceSbjtCnt":null,"corsYy":"2019","subInspTotalPnt":null,"abeekGrpNm":"","rowStatus":1,"theoFg":"U0210001","curiNo":"2019106214"},{"submattFg":"U0209001","stgNeceGrpNm":"","sideTotalPnt":1.0,"sbjtChgFg":"","subDgnTotalPnt":null,"sy62shtmRcomYn":"","abeekSubmattFgNm":"","sustLsnFgNm":"전필","sy12shtmRcomYn":"","sy42shtmRcomYn":"○","abeekInspPracPntCnt":null,"genrl1stgNeceSbjtCnt":null,"abeekSustLsnFg":"","abeekDetaSubmattFg":"","sy51shtmRcomYn":"","abeekSustLsnFgNm":"","sy11shtmRcomYn":"","abeekTheoPntCnt":null,"sy31shtmRcomYn":"","submattFgNm":"전공과목","sbjtCd":"MED4014","subTheoTotalPnt":null,"mjCd":"DS03008002001","sy61shtmRcomYn":"","sy22shtmRcomYn":"","mjCdNm":"의학전공(과)","sustLsnFg":"U0208004","sy52shtmRcomYn":"","sy21shtmRcomYn":"","sbjtChgFgNm":"","abeekDgnPntCnt":null,"sbjtKorNm":"기초의학종합평가","sy41shtmRcomYn":"","genrl1stgNeceGrp":"","abeekGrpChoice":"","abeekSubmattFg":"","theoFgNm":"이론","abeekDetaSubmattFgNm":"","sy32shtmRcomYn":"","openTm":1.0,"pnt":1.0,"sbjtId":"20100275","abeekChoiceSbjtCnt":null,"corsYy":"2019","subInspTotalPnt":null,"abeekGrpNm":"","rowStatus":1,"theoFg":"U0210001","curiNo":"2019106215"},{"submattFg":"U0209001","stgNeceGrpNm":"","sideTotalPnt":2.0,"sbjtChgFg":"","subDgnTotalPnt":null,"sy62shtmRcomYn":"","abeekSubmattFgNm":"","sustLsnFgNm":"전필","sy12shtmRcomYn":"","sy42shtmRcomYn":"","abeekInspPracPntCnt":null,"genrl1stgNeceSbjtCnt":null,"abeekSustLsnFg":"","abeekDetaSubmattFg":"","sy51shtmRcomYn":"","abeekSustLsnFgNm":"","sy11shtmRcomYn":"","abeekTheoPntCnt":null,"sy31shtmRcomYn":"","submattFgNm":"전공과목","sbjtCd":"MED4016","subTheoTotalPnt":null,"mjCd":"DS03008002001","sy61shtmRcomYn":"","sy22shtmRcomYn":"","mjCdNm":"의학전공(과)","sustLsnFg":"U0208004","sy52shtmRcomYn":"","sy21shtmRcomYn":"","sbjtChgFgNm":"","abeekDgnPntCnt":null,"sbjtKorNm":"임상실습입문 2","sy41shtmRcomYn":"○","genrl1stgNeceGrp":"","abeekGrpChoice":"","abeekSubmattFg":"","theoFgNm":"실습","abeekDetaSubmattFgNm":"","sy32shtmRcomYn":"","openTm":2.0,"pnt":2.0,"sbjtId":"20110649","abeekChoiceSbjtCnt":null,"corsYy":"2019","subInspTotalPnt":null,"abeekGrpNm":"","rowStatus":1,"theoFg":"U0210002","curiNo":"2019106216"},{"submattFg":"U0209001","stgNeceGrpNm":"","sideTotalPnt":2.0,"sbjtChgFg":"","subDgnTotalPnt":null,"sy62shtmRcomYn":"","abeekSubmattFgNm":"","sustLsnFgNm":"전필","sy12shtmRcomYn":"","sy42shtmRcomYn":"○","abeekInspPracPntCnt":null,"genrl1stgNeceSbjtCnt":null,"abeekSustLsnFg":"","abeekDetaSubmattFg":"","sy51shtmRcomYn":"","abeekSustLsnFgNm":"","sy11shtmRcomYn":"","abeekTheoPntCnt":null,"sy31shtmRcomYn":"","submattFgNm":"전공과목","sbjtCd":"MED4018","subTheoTotalPnt":null,"mjCd":"DS03008002001","sy61shtmRcomYn":"","sy22shtmRcomYn":"","mjCdNm":"의학전공(과)","sustLsnFg":"U0208004","sy52shtmRcomYn":"","sy21shtmRcomYn":"","sbjtChgFgNm":"","abeekDgnPntCnt":null,"sbjtKorNm":"환자/의사/사회 2","sy41shtmRcomYn":"","genrl1stgNeceGrp":"","abeekGrpChoice":"","abeekSubmattFg":"","theoFgNm":"이론","abeekDetaSubmattFgNm":"","sy32shtmRcomYn":"","openTm":2.0,"pnt":2.0,"sbjtId":"20120181","abeekChoiceSbjtCnt":null,"corsYy":"2019","subInspTotalPnt":null,"abeekGrpNm":"","rowStatus":1,"theoFg":"U0210001","curiNo":"2019106217"},{"submattFg":"U0209001","stgNeceGrpNm":"","sideTotalPnt":3.0,"sbjtChgFg":"","subDgnTotalPnt":null,"sy62shtmRcomYn":"","abeekSubmattFgNm":"","sustLsnFgNm":"전필","sy12shtmRcomYn":"","sy42shtmRcomYn":"","abeekInspPracPntCnt":null,"genrl1stgNeceSbjtCnt":null,"abeekSustLsnFg":"","abeekDetaSubmattFg":"","sy51shtmRcomYn":"","abeekSustLsnFgNm":"","sy11shtmRcomYn":"","abeekTheoPntCnt":null,"sy31shtmRcomYn":"","submattFgNm":"전공과목","sbjtCd":"MED4019","subTheoTotalPnt":null,"mjCd":"DS03008002001","sy61shtmRcomYn":"","sy22shtmRcomYn":"","mjCdNm":"의학전공(과)","sustLsnFg":"U0208004","sy52shtmRcomYn":"","sy21shtmRcomYn":"","sbjtChgFgNm":"","abeekDgnPntCnt":null,"sbjtKorNm":"성장과 발달","sy41shtmRcomYn":"○","genrl1stgNeceGrp":"","abeekGrpChoice":"","abeekSubmattFg":"","theoFgNm":"이론","abeekDetaSubmattFgNm":"","sy32shtmRcomYn":"","openTm":2.0,"pnt":3.0,"sbjtId":"20130394","abeekChoiceSbjtCnt":null,"corsYy":"2019","subInspTotalPnt":null,"abeekGrpNm":"","rowStatus":1,"theoFg":"U0210001","curiNo":"2019106218"},{"submattFg":"U0209001","stgNeceGrpNm":"","sideTotalPnt":5.0,"sbjtChgFg":"","subDgnTotalPnt":null,"sy62shtmRcomYn":"","abeekSubmattFgNm":"","sustLsnFgNm":"전필","sy12shtmRcomYn":"","sy42shtmRcomYn":"","abeekInspPracPntCnt":null,"genrl1stgNeceSbjtCnt":null,"abeekSustLsnFg":"","abeekDetaSubmattFg":"","sy51shtmRcomYn":"","abeekSustLsnFgNm":"","sy11shtmRcomYn":"","abeekTheoPntCnt":null,"sy31shtmRcomYn":"","submattFgNm":"전공과목","sbjtCd":"MED402","subTheoTotalPnt":null,"mjCd":"DS03008002001","sy61shtmRcomYn":"","sy22shtmRcomYn":"","mjCdNm":"의학전공(과)","sustLsnFg":"U0208004","sy52shtmRcomYn":"","sy21shtmRcomYn":"","sbjtChgFgNm":"","abeekDgnPntCnt":null,"sbjtKorNm":"신장비뇨기","sy41shtmRcomYn":"○","genrl1stgNeceGrp":"","abeekGrpChoice":"","abeekSubmattFg":"","theoFgNm":"이론+실습","abeekDetaSubmattFgNm":"","sy32shtmRcomYn":"","openTm":5.0,"pnt":5.0,"sbjtId":"40011","abeekChoiceSbjtCnt":null,"corsYy":"2019","subInspTotalPnt":null,"abeekGrpNm":"","rowStatus":1,"theoFg":"U0210005","curiNo":"2019106219"},{"submattFg":"U0209001","stgNeceGrpNm":"","sideTotalPnt":5.0,"sbjtChgFg":"","subDgnTotalPnt":null,"sy62shtmRcomYn":"","abeekSubmattFgNm":"","sustLsnFgNm":"전필","sy12shtmRcomYn":"","sy42shtmRcomYn":"","abeekInspPracPntCnt":null,"genrl1stgNeceSbjtCnt":null,"abeekSustLsnFg":"","abeekDetaSubmattFg":"","sy51shtmRcomYn":"","abeekSustLsnFgNm":"","sy11shtmRcomYn":"","abeekTheoPntCnt":null,"sy31shtmRcomYn":"","submattFgNm":"전공과목","sbjtCd":"MED403","subTheoTotalPnt":null,"mjCd":"DS03008002001","sy61shtmRcomYn":"","sy22shtmRcomYn":"","mjCdNm":"의학전공(과)","sustLsnFg":"U0208004","sy52shtmRcomYn":"","sy21shtmRcomYn":"","sbjtChgFgNm":"","abeekDgnPntCnt":null,"sbjtKorNm":"혈액과 종양","sy41shtmRcomYn":"○","genrl1stgNeceGrp":"","abeekGrpChoice":"","abeekSubmattFg":"","theoFgNm":"이론+실습","abeekDetaSubmattFgNm":"","sy32shtmRcomYn":"","openTm":5.0,"pnt":5.0,"sbjtId":"40012","abeekChoiceSbjtCnt":null,"corsYy":"2019","subInspTotalPnt":null,"abeekGrpNm":"","rowStatus":1,"theoFg":"U0210005","curiNo":"2019106220"},{"submattFg":"U0209001","stgNeceGrpNm":"","sideTotalPnt":6.0,"sbjtChgFg":"","subDgnTotalPnt":null,"sy62shtmRcomYn":"","abeekSubmattFgNm":"","sustLsnFgNm":"전필","sy12shtmRcomYn":"","sy42shtmRcomYn":"","abeekInspPracPntCnt":null,"genrl1stgNeceSbjtCnt":null,"abeekSustLsnFg":"","abeekDetaSubmattFg":"","sy51shtmRcomYn":"","abeekSustLsnFgNm":"","sy11shtmRcomYn":"","abeekTheoPntCnt":null,"sy31shtmRcomYn":"","submattFgNm":"전공과목","sbjtCd":"MED404","subTheoTotalPnt":null,"mjCd":"DS03008002001","sy61shtmRcomYn":"","sy22shtmRcomYn":"","mjCdNm":"의학전공(과)","sustLsnFg":"U0208004","sy52shtmRcomYn":"","sy21shtmRcomYn":"","sbjtChgFgNm":"","abeekDgnPntCnt":null,"sbjtKorNm":"내분비","sy41shtmRcomYn":"○","genrl1stgNeceGrp":"","abeekGrpChoice":"","abeekSubmattFg":"","theoFgNm":"이론+실습","abeekDetaSubmattFgNm":"","sy32shtmRcomYn":"","openTm":6.0,"pnt":6.0,"sbjtId":"40013","abeekChoiceSbjtCnt":null,"corsYy":"2019","subInspTotalPnt":null,"abeekGrpNm":"","rowStatus":1,"theoFg":"U0210005","curiNo":"2019106221"},{"submattFg":"U0209001","stgNeceGrpNm":"","sideTotalPnt":5.0,"sbjtChgFg":"","subDgnTotalPnt":null,"sy62shtmRcomYn":"","abeekSubmattFgNm":"","sustLsnFgNm":"전필","sy12shtmRcomYn":"","sy42shtmRcomYn":"","abeekInspPracPntCnt":null,"genrl1stgNeceSbjtCnt":null,"abeekSustLsnFg":"","abeekDetaSubmattFg":"","sy51shtmRcomYn":"","abeekSustLsnFgNm":"","sy11shtmRcomYn":"","abeekTheoPntCnt":null,"sy31shtmRcomYn":"","submattFgNm":"전공과목","sbjtCd":"MED405","subTheoTotalPnt":null,"mjCd":"DS03008002001","sy61shtmRcomYn":"","sy22shtmRcomYn":"","mjCdNm":"의학전공(과)","sustLsnFg":"U0208004","sy52shtmRcomYn":"","sy21shtmRcomYn":"","sbjtChgFgNm":"","abeekDgnPntCnt":null,"sbjtKorNm":"두경부와 피부","sy41shtmRcomYn":"○","genrl1stgNeceGrp":"","abeekGrpChoice":"","abeekSubmattFg":"","theoFgNm":"이론+실습","abeekDetaSubmattFgNm":"","sy32shtmRcomYn":"","openTm":5.0,"pnt":5.0,"sbjtId":"40014","abeekChoiceSbjtCnt":null,"corsYy":"2019","subInspTotalPnt":null,"abeekGrpNm":"","rowStatus":1,"theoFg":"U0210005","curiNo":"2019106222"},{"submattFg":"U0209001","stgNeceGrpNm":"","sideTotalPnt":6.0,"sbjtChgFg":"","subDgnTotalPnt":null,"sy62shtmRcomYn":"","abeekSubmattFgNm":"","sustLsnFgNm":"전필","sy12shtmRcomYn":"","sy42shtmRcomYn":"○","abeekInspPracPntCnt":null,"genrl1stgNeceSbjtCnt":null,"abeekSustLsnFg":"","abeekDetaSubmattFg":"","sy51shtmRcomYn":"","abeekSustLsnFgNm":"","sy11shtmRcomYn":"","abeekTheoPntCnt":null,"sy31shtmRcomYn":"","submattFgNm":"전공과목","sbjtCd":"MED407","subTheoTotalPnt":null,"mjCd":"DS03008002001","sy61shtmRcomYn":"","sy22shtmRcomYn":"","mjCdNm":"의학전공(과)","sustLsnFg":"U0208004","sy52shtmRcomYn":"","sy21shtmRcomYn":"","sbjtChgFgNm":"","abeekDgnPntCnt":null,"sbjtKorNm":"생식기","sy41shtmRcomYn":"","genrl1stgNeceGrp":"","abeekGrpChoice":"","abeekSubmattFg":"","theoFgNm":"이론","abeekDetaSubmattFgNm":"","sy32shtmRcomYn":"","openTm":6.0,"pnt":6.0,"sbjtId":"40016","abeekChoiceSbjtCnt":null,"corsYy":"2019","subInspTotalPnt":null,"abeekGrpNm":"","rowStatus":1,"theoFg":"U0210001","curiNo":"2019106223"},{"submattFg":"U0209001","stgNeceGrpNm":"","sideTotalPnt":3.0,"sbjtChgFg":"","subDgnTotalPnt":null,"sy62shtmRcomYn":"","abeekSubmattFgNm":"","sustLsnFgNm":"전필","sy12shtmRcomYn":"","sy42shtmRcomYn":"○","abeekInspPracPntCnt":null,"genrl1stgNeceSbjtCnt":null,"abeekSustLsnFg":"","abeekDetaSubmattFg":"","sy51shtmRcomYn":"","abeekSustLsnFgNm":"","sy11shtmRcomYn":"","abeekTheoPntCnt":null,"sy31shtmRcomYn":"","submattFgNm":"전공과목","sbjtCd":"MED408","subTheoTotalPnt":null,"mjCd":"DS03008002001","sy61shtmRcomYn":"","sy22shtmRcomYn":"","mjCdNm":"의학전공(과)","sustLsnFg":"U0208004","sy52shtmRcomYn":"","sy21shtmRcomYn":"","sbjtChgFgNm":"","abeekDgnPntCnt":null,"sbjtKorNm":"근골격","sy41shtmRcomYn":"","genrl1stgNeceGrp":"","abeekGrpChoice":"","abeekSubmattFg":"","theoFgNm":"이론","abeekDetaSubmattFgNm":"","sy32shtmRcomYn":"","openTm":3.0,"pnt":3.0,"sbjtId":"40017","abeekChoiceSbjtCnt":null,"corsYy":"2019","subInspTotalPnt":null,"abeekGrpNm":"","rowStatus":1,"theoFg":"U0210001","curiNo":"2019106224"},{"submattFg":"U0209001","stgNeceGrpNm":"","sideTotalPnt":6.0,"sbjtChgFg":"","subDgnTotalPnt":null,"sy62shtmRcomYn":"","abeekSubmattFgNm":"","sustLsnFgNm":"전필","sy12shtmRcomYn":"","sy42shtmRcomYn":"○","abeekInspPracPntCnt":null,"genrl1stgNeceSbjtCnt":null,"abeekSustLsnFg":"","abeekDetaSubmattFg":"","sy51shtmRcomYn":"","abeekSustLsnFgNm":"","sy11shtmRcomYn":"","abeekTheoPntCnt":null,"sy31shtmRcomYn":"","submattFgNm":"전공과목","sbjtCd":"MED409","subTheoTotalPnt":null,"mjCd":"DS03008002001","sy61shtmRcomYn":"","sy22shtmRcomYn":"","mjCdNm":"의학전공(과)","sustLsnFg":"U0208004","sy52shtmRcomYn":"","sy21shtmRcomYn":"","sbjtChgFgNm":"","abeekDgnPntCnt":null,"sbjtKorNm":"신경","sy41shtmRcomYn":"","genrl1stgNeceGrp":"","abeekGrpChoice":"","abeekSubmattFg":"","theoFgNm":"이론","abeekDetaSubmattFgNm":"","sy32shtmRcomYn":"","openTm":6.0,"pnt":6.0,"sbjtId":"40018","abeekChoiceSbjtCnt":null,"corsYy":"2019","subInspTotalPnt":null,"abeekGrpNm":"","rowStatus":1,"theoFg":"U0210001","curiNo":"2019106151"},{"submattFg":"U0209001","stgNeceGrpNm":"","sideTotalPnt":1.0,"sbjtChgFg":"","subDgnTotalPnt":null,"sy62shtmRcomYn":"","abeekSubmattFgNm":"","sustLsnFgNm":"전필","sy12shtmRcomYn":"","sy42shtmRcomYn":"","abeekInspPracPntCnt":null,"genrl1stgNeceSbjtCnt":null,"abeekSustLsnFg":"","abeekDetaSubmattFg":"","sy51shtmRcomYn":"○","abeekSustLsnFgNm":"","sy11shtmRcomYn":"","abeekTheoPntCnt":null,"sy31shtmRcomYn":"","submattFgNm":"전공과목","sbjtCd":"MED501","subTheoTotalPnt":null,"mjCd":"DS03008002001","sy61shtmRcomYn":"","sy22shtmRcomYn":"","mjCdNm":"의학전공(과)","sustLsnFg":"U0208004","sy52shtmRcomYn":"○","sy21shtmRcomYn":"","sbjtChgFgNm":"","abeekDgnPntCnt":null,"sbjtKorNm":"멘토와의 대화 3","sy41shtmRcomYn":"","genrl1stgNeceGrp":"","abeekGrpChoice":"","abeekSubmattFg":"","theoFgNm":"이론","abeekDetaSubmattFgNm":"","sy32shtmRcomYn":"","openTm":1.0,"pnt":1.0,"sbjtId":"40043","abeekChoiceSbjtCnt":null,"corsYy":"2019","subInspTotalPnt":null,"abeekGrpNm":"","rowStatus":1,"theoFg":"U0210001","curiNo":"2019106152"},{"submattFg":"U0209001","stgNeceGrpNm":"","sideTotalPnt":2.0,"sbjtChgFg":"","subDgnTotalPnt":null,"sy62shtmRcomYn":"","abeekSubmattFgNm":"","sustLsnFgNm":"전필","sy12shtmRcomYn":"","sy42shtmRcomYn":"","abeekInspPracPntCnt":null,"genrl1stgNeceSbjtCnt":null,"abeekSustLsnFg":"","abeekDetaSubmattFg":"","sy51shtmRcomYn":"○","abeekSustLsnFgNm":"","sy11shtmRcomYn":"","abeekTheoPntCnt":null,"sy31shtmRcomYn":"","submattFgNm":"전공과목","sbjtCd":"MED505","subTheoTotalPnt":null,"mjCd":"DS03008002001","sy61shtmRcomYn":"","sy22shtmRcomYn":"","mjCdNm":"의학전공(과)","sustLsnFg":"U0208004","sy52shtmRcomYn":"○","sy21shtmRcomYn":"","sbjtChgFgNm":"","abeekDgnPntCnt":null,"sbjtKorNm":"환자/의사/사회 3","sy41shtmRcomYn":"","genrl1stgNeceGrp":"","abeekGrpChoice":"","abeekSubmattFg":"","theoFgNm":"이론","abeekDetaSubmattFgNm":"","sy32shtmRcomYn":"","openTm":2.0,"pnt":2.0,"sbjtId":"20110647","abeekChoiceSbjtCnt":null,"corsYy":"2019","subInspTotalPnt":null,"abeekGrpNm":"","rowStatus":1,"theoFg":"U0210001","curiNo":"2019106154"},{"submattFg":"U0209001","stgNeceGrpNm":"","sideTotalPnt":2.0,"sbjtChgFg":"","subDgnTotalPnt":null,"sy62shtmRcomYn":"","abeekSubmattFgNm":"","sustLsnFgNm":"전필","sy12shtmRcomYn":"","sy42shtmRcomYn":"","abeekInspPracPntCnt":null,"genrl1stgNeceSbjtCnt":null,"abeekSustLsnFg":"","abeekDetaSubmattFg":"","sy51shtmRcomYn":"○","abeekSustLsnFgNm":"","sy11shtmRcomYn":"","abeekTheoPntCnt":null,"sy31shtmRcomYn":"","submattFgNm":"전공과목","sbjtCd":"MED506","subTheoTotalPnt":null,"mjCd":"DS03008002001","sy61shtmRcomYn":"","sy22shtmRcomYn":"","mjCdNm":"의학전공(과)","sustLsnFg":"U0208004","sy52shtmRcomYn":"○","sy21shtmRcomYn":"","sbjtChgFgNm":"","abeekDgnPntCnt":null,"sbjtKorNm":"임상실습입문 3","sy41shtmRcomYn":"","genrl1stgNeceGrp":"","abeekGrpChoice":"","abeekSubmattFg":"","theoFgNm":"실습","abeekDetaSubmattFgNm":"","sy32shtmRcomYn":"","openTm":2.0,"pnt":2.0,"sbjtId":"20110650","abeekChoiceSbjtCnt":null,"corsYy":"2019","subInspTotalPnt":null,"abeekGrpNm":"","rowStatus":1,"theoFg":"U0210002","curiNo":"2019106155"},{"submattFg":"U0209001","stgNeceGrpNm":"","sideTotalPnt":1.0,"sbjtChgFg":"U0212002","subDgnTotalPnt":null,"sy62shtmRcomYn":"","abeekSubmattFgNm":"","sustLsnFgNm":"전필","sy12shtmRcomYn":"","sy42shtmRcomYn":"","abeekInspPracPntCnt":null,"genrl1stgNeceSbjtCnt":null,"abeekSustLsnFg":"","abeekDetaSubmattFg":"","sy51shtmRcomYn":"○","abeekSustLsnFgNm":"","sy11shtmRcomYn":"","abeekTheoPntCnt":null,"sy31shtmRcomYn":"","submattFgNm":"전공과목","sbjtCd":"MED507","subTheoTotalPnt":null,"mjCd":"DS03008002001","sy61shtmRcomYn":"","sy22shtmRcomYn":"","mjCdNm":"의학전공(과)","sustLsnFg":"U0208004","sy52shtmRcomYn":"○","sy21shtmRcomYn":"","sbjtChgFgNm":"변경","abeekDgnPntCnt":null,"sbjtKorNm":"임상의학종합평가1","sy41shtmRcomYn":"","genrl1stgNeceGrp":"","abeekGrpChoice":"","abeekSubmattFg":"","theoFgNm":"이론","abeekDetaSubmattFgNm":"","sy32shtmRcomYn":"","openTm":1.0,"pnt":1.0,"sbjtId":"20180384","abeekChoiceSbjtCnt":null,"corsYy":"2019","subInspTotalPnt":null,"abeekGrpNm":"","rowStatus":1,"theoFg":"U0210001","curiNo":"2019106153"},{"submattFg":"U0209001","stgNeceGrpNm":"","sideTotalPnt":1.0,"sbjtChgFg":"","subDgnTotalPnt":null,"sy62shtmRcomYn":"○","abeekSubmattFgNm":"","sustLsnFgNm":"전필","sy12shtmRcomYn":"","sy42shtmRcomYn":"","abeekInspPracPntCnt":null,"genrl1stgNeceSbjtCnt":null,"abeekSustLsnFg":"","abeekDetaSubmattFg":"","sy51shtmRcomYn":"","abeekSustLsnFgNm":"","sy11shtmRcomYn":"","abeekTheoPntCnt":null,"sy31shtmRcomYn":"","submattFgNm":"전공과목","sbjtCd":"MED601","subTheoTotalPnt":null,"mjCd":"DS03008002001","sy61shtmRcomYn":"○","sy22shtmRcomYn":"","mjCdNm":"의학전공(과)","sustLsnFg":"U0208004","sy52shtmRcomYn":"","sy21shtmRcomYn":"","sbjtChgFgNm":"","abeekDgnPntCnt":null,"sbjtKorNm":"멘토와의 대화 4","sy41shtmRcomYn":"","genrl1stgNeceGrp":"","abeekGrpChoice":"","abeekSubmattFg":"","theoFgNm":"이론","abeekDetaSubmattFgNm":"","sy32shtmRcomYn":"","openTm":1.0,"pnt":1.0,"sbjtId":"40040","abeekChoiceSbjtCnt":null,"corsYy":"2019","subInspTotalPnt":null,"abeekGrpNm":"","rowStatus":1,"theoFg":"U0210001","curiNo":"2019106156"},{"submattFg":"U0209001","stgNeceGrpNm":"","sideTotalPnt":2.0,"sbjtChgFg":"","subDgnTotalPnt":null,"sy62shtmRcomYn":"○","abeekSubmattFgNm":"","sustLsnFgNm":"전필","sy12shtmRcomYn":"","sy42shtmRcomYn":"","abeekInspPracPntCnt":null,"genrl1stgNeceSbjtCnt":null,"abeekSustLsnFg":"","abeekDetaSubmattFg":"","sy51shtmRcomYn":"","abeekSustLsnFgNm":"","sy11shtmRcomYn":"","abeekTheoPntCnt":null,"sy31shtmRcomYn":"","submattFgNm":"전공과목","sbjtCd":"MED6011","subTheoTotalPnt":null,"mjCd":"DS03008002001","sy61shtmRcomYn":"○","sy22shtmRcomYn":"","mjCdNm":"의학전공(과)","sustLsnFg":"U0208004","sy52shtmRcomYn":"","sy21shtmRcomYn":"","sbjtChgFgNm":"","abeekDgnPntCnt":null,"sbjtKorNm":"환자/의사/사회 4","sy41shtmRcomYn":"","genrl1stgNeceGrp":"","abeekGrpChoice":"","abeekSubmattFg":"","theoFgNm":"이론","abeekDetaSubmattFgNm":"","sy32shtmRcomYn":"","openTm":null,"pnt":2.0,"sbjtId":"20110510","abeekChoiceSbjtCnt":null,"corsYy":"2019","subInspTotalPnt":null,"abeekGrpNm":"","rowStatus":1,"theoFg":"U0210001","curiNo":"2019106157"},{"submattFg":"U0209001","stgNeceGrpNm":"","sideTotalPnt":2.0,"sbjtChgFg":"","subDgnTotalPnt":null,"sy62shtmRcomYn":"○","abeekSubmattFgNm":"","sustLsnFgNm":"전필","sy12shtmRcomYn":"","sy42shtmRcomYn":"","abeekInspPracPntCnt":null,"genrl1stgNeceSbjtCnt":null,"abeekSustLsnFg":"","abeekDetaSubmattFg":"","sy51shtmRcomYn":"","abeekSustLsnFgNm":"","sy11shtmRcomYn":"","abeekTheoPntCnt":null,"sy31shtmRcomYn":"","submattFgNm":"전공과목","sbjtCd":"MED6018","subTheoTotalPnt":null,"mjCd":"DS03008002001","sy61shtmRcomYn":"○","sy22shtmRcomYn":"","mjCdNm":"의학전공(과)","sustLsnFg":"U0208004","sy52shtmRcomYn":"","sy21shtmRcomYn":"","sbjtChgFgNm":"","abeekDgnPntCnt":null,"sbjtKorNm":"직업환경의학실습","sy41shtmRcomYn":"","genrl1stgNeceGrp":"","abeekGrpChoice":"","abeekSubmattFg":"","theoFgNm":"실습","abeekDetaSubmattFgNm":"","sy32shtmRcomYn":"","openTm":2.0,"pnt":2.0,"sbjtId":"20130186","abeekChoiceSbjtCnt":null,"corsYy":"2019","subInspTotalPnt":null,"abeekGrpNm":"","rowStatus":1,"theoFg":"U0210002","curiNo":"2019106158"},{"submattFg":"U0209001","stgNeceGrpNm":"","sideTotalPnt":2.0,"sbjtChgFg":"","subDgnTotalPnt":null,"sy62shtmRcomYn":"○","abeekSubmattFgNm":"","sustLsnFgNm":"전필","sy12shtmRcomYn":"","sy42shtmRcomYn":"","abeekInspPracPntCnt":null,"genrl1stgNeceSbjtCnt":null,"abeekSustLsnFg":"","abeekDetaSubmattFg":"","sy51shtmRcomYn":"","abeekSustLsnFgNm":"","sy11shtmRcomYn":"","abeekTheoPntCnt":null,"sy31shtmRcomYn":"","submattFgNm":"전공과목","sbjtCd":"MED6023","subTheoTotalPnt":null,"mjCd":"DS03008002001","sy61shtmRcomYn":"○","sy22shtmRcomYn":"","mjCdNm":"의학전공(과)","sustLsnFg":"U0208004","sy52shtmRcomYn":"","sy21shtmRcomYn":"","sbjtChgFgNm":"","abeekDgnPntCnt":null,"sbjtKorNm":"외상의학실습","sy41shtmRcomYn":"","genrl1stgNeceGrp":"","abeekGrpChoice":"","abeekSubmattFg":"","theoFgNm":"실습","abeekDetaSubmattFgNm":"","sy32shtmRcomYn":"","openTm":2.0,"pnt":2.0,"sbjtId":"20160391","abeekChoiceSbjtCnt":null,"corsYy":"2019","subInspTotalPnt":null,"abeekGrpNm":"","rowStatus":1,"theoFg":"U0210002","curiNo":"2019106159"},{"submattFg":"U0209001","stgNeceGrpNm":"","sideTotalPnt":1.0,"sbjtChgFg":"U0212001","subDgnTotalPnt":null,"sy62shtmRcomYn":"○","abeekSubmattFgNm":"","sustLsnFgNm":"전필","sy12shtmRcomYn":"","sy42shtmRcomYn":"","abeekInspPracPntCnt":null,"genrl1stgNeceSbjtCnt":null,"abeekSustLsnFg":"","abeekDetaSubmattFg":"","sy51shtmRcomYn":"","abeekSustLsnFgNm":"","sy11shtmRcomYn":"","abeekTheoPntCnt":null,"sy31shtmRcomYn":"","submattFgNm":"전공과목","sbjtCd":"MED6024","subTheoTotalPnt":null,"mjCd":"DS03008002001","sy61shtmRcomYn":"○","sy22shtmRcomYn":"","mjCdNm":"의학전공(과)","sustLsnFg":"U0208004","sy52shtmRcomYn":"","sy21shtmRcomYn":"","sbjtChgFgNm":"신설","abeekDgnPntCnt":null,"sbjtKorNm":"임상의학종합평가2","sy41shtmRcomYn":"","genrl1stgNeceGrp":"","abeekGrpChoice":"","abeekSubmattFg":"","theoFgNm":"이론","abeekDetaSubmattFgNm":"","sy32shtmRcomYn":"","openTm":1.0,"pnt":1.0,"sbjtId":"20180383","abeekChoiceSbjtCnt":null,"corsYy":"2019","subInspTotalPnt":null,"abeekGrpNm":"","rowStatus":1,"theoFg":"U0210001","curiNo":"2019107727"},{"submattFg":"U0209001","stgNeceGrpNm":"","sideTotalPnt":1.0,"sbjtChgFg":"","subDgnTotalPnt":null,"sy62shtmRcomYn":"○","abeekSubmattFgNm":"","sustLsnFgNm":"전필","sy12shtmRcomYn":"","sy42shtmRcomYn":"","abeekInspPracPntCnt":null,"genrl1stgNeceSbjtCnt":null,"abeekSustLsnFg":"","abeekDetaSubmattFg":"","sy51shtmRcomYn":"","abeekSustLsnFgNm":"","sy11shtmRcomYn":"","abeekTheoPntCnt":null,"sy31shtmRcomYn":"","submattFgNm":"전공과목","sbjtCd":"MED605","subTheoTotalPnt":null,"mjCd":"DS03008002001","sy61shtmRcomYn":"○","sy22shtmRcomYn":"","mjCdNm":"의학전공(과)","sustLsnFg":"U0208004","sy52shtmRcomYn":"","sy21shtmRcomYn":"","sbjtChgFgNm":"","abeekDgnPntCnt":null,"sbjtKorNm":"임상실습입문 4","sy41shtmRcomYn":"","genrl1stgNeceGrp":"","abeekGrpChoice":"","abeekSubmattFg":"","theoFgNm":"실습","abeekDetaSubmattFgNm":"","sy32shtmRcomYn":"","openTm":1.0,"pnt":1.0,"sbjtId":"20100616","abeekChoiceSbjtCnt":null,"corsYy":"2019","subInspTotalPnt":null,"abeekGrpNm":"","rowStatus":1,"theoFg":"U0210002","curiNo":"2019106160"},{"submattFg":"U0209001","stgNeceGrpNm":"","sideTotalPnt":6.0,"sbjtChgFg":"","subDgnTotalPnt":null,"sy62shtmRcomYn":"","abeekSubmattFgNm":"","sustLsnFgNm":"전선","sy12shtmRcomYn":"","sy42shtmRcomYn":"","abeekInspPracPntCnt":null,"genrl1stgNeceSbjtCnt":null,"abeekSustLsnFg":"","abeekDetaSubmattFg":"","sy51shtmRcomYn":"","abeekSustLsnFgNm":"","sy11shtmRcomYn":"","abeekTheoPntCnt":null,"sy31shtmRcomYn":"","submattFgNm":"전공과목","sbjtCd":"MED206","subTheoTotalPnt":null,"mjCd":"DS03008002001","sy61shtmRcomYn":"","sy22shtmRcomYn":"","mjCdNm":"의학전공(과)","sustLsnFg":"U0208005","sy52shtmRcomYn":"","sy21shtmRcomYn":"○","sbjtChgFgNm":"","abeekDgnPntCnt":null,"sbjtKorNm":"의과학기초연구 2","sy41shtmRcomYn":"","genrl1stgNeceGrp":"","abeekGrpChoice":"","abeekSubmattFg":"","theoFgNm":"이론+실습","abeekDetaSubmattFgNm":"","sy32shtmRcomYn":"","openTm":12.0,"pnt":6.0,"sbjtId":"20120862","abeekChoiceSbjtCnt":null,"corsYy":"2019","subInspTotalPnt":null,"abeekGrpNm":"","rowStatus":1,"theoFg":"U0210005","curiNo":"2019106225"}]}}